[
  {
    "gameId": 587,
    "word": "acólita",
    "url": "https://lapalabradeldia.com/personalizada/?p=YWPDs2xpdGE%3D&t=true"
  },
  {
    "gameId": 586,
    "word": "viático",
    "url": "https://lapalabradeldia.com/personalizada/?p=dmnDoXRpY28%3D&t=true"
  },
  {
    "gameId": 583,
    "word": "enésimo",
    "url": "https://lapalabradeldia.com/personalizada/?p=ZW7DqXNpbW8%3D&t=true"
  },
  {
    "gameId": 582,
    "word": "clásica",
    "url": "https://lapalabradeldia.com/personalizada/?p=Y2zDoXNpY2E%3D&t=true"
  },
  {
    "gameId": 581,
    "word": "coatí",
    "url": "https://lapalabradeldia.com/personalizada/?p=Y29hdMOt&t=true"
  },
  {
    "gameId": 580,
    "word": "gótico",
    "url": "https://lapalabradeldia.com/personalizada/?p=Z8OzdGljbw%3D%3D&t=true"
  },
  {
    "gameId": 579,
    "word": "sofreír",
    "url": "https://lapalabradeldia.com/personalizada/?p=c29mcmXDrXI%3D&t=true"
  },
  {
    "gameId": 578,
    "word": "vértigo",
    "url": "https://lapalabradeldia.com/personalizada/?p=dsOpcnRpZ28%3D&t=true"
  },
  {
    "gameId": 577,
    "word": "alógica",
    "url": "https://lapalabradeldia.com/personalizada/?p=YWzDs2dpY2E%3D&t=true"
  },
  {
    "gameId": 576,
    "word": "idílica",
    "url": "https://lapalabradeldia.com/personalizada/?p=aWTDrWxpY2E%3D&t=true"
  },
  {
    "gameId": 575,
    "word": "eufonía",
    "url": "https://lapalabradeldia.com/personalizada/?p=ZXVmb27DrWE%3D&t=true"
  },
  {
    "gameId": 574,
    "word": "pulmón",
    "url": "https://lapalabradeldia.com/personalizada/?p=cHVsbcOzbg%3D%3D&t=true"
  },
  {
    "gameId": 573,
    "word": "maoísmo",
    "url": "https://lapalabradeldia.com/personalizada/?p=bWFvw61zbW8%3D&t=true"
  },
  {
    "gameId": 572,
    "word": "récord",
    "url": "https://lapalabradeldia.com/personalizada/?p=csOpY29yZA%3D%3D&t=true"
  },
  {
    "gameId": 571,
    "word": "colchón",
    "url": "https://lapalabradeldia.com/personalizada/?p=Y29sY2jDs24%3D&t=true"
  },
  {
    "gameId": 570,
    "word": "fúlgido",
    "url": "https://lapalabradeldia.com/personalizada/?p=ZsO6bGdpZG8%3D&t=true"
  },
  {
    "gameId": 569,
    "word": "séptico",
    "url": "https://lapalabradeldia.com/personalizada/?p=c8OpcHRpY28%3D&t=true"
  },
  {
    "gameId": 568,
    "word": "búnker",
    "url": "https://lapalabradeldia.com/personalizada/?p=YsO6bmtlcg%3D%3D&t=true"
  },
  {
    "gameId": 567,
    "word": "culón",
    "url": "https://lapalabradeldia.com/personalizada/?p=Y3Vsw7Nu&t=true"
  },
  {
    "gameId": 566,
    "word": "pálpito",
    "url": "https://lapalabradeldia.com/personalizada/?p=cMOhbHBpdG8%3D&t=true"
  },
  {
    "gameId": 565,
    "word": "súbito",
    "url": "https://lapalabradeldia.com/personalizada/?p=c8O6Yml0bw%3D%3D&t=true"
  },
  {
    "gameId": 564,
    "word": "trémolo",
    "url": "https://lapalabradeldia.com/personalizada/?p=dHLDqW1vbG8%3D&t=true"
  },
  {
    "gameId": 563,
    "word": "fustán",
    "url": "https://lapalabradeldia.com/personalizada/?p=ZnVzdMOhbg%3D%3D&t=true"
  },
  {
    "gameId": 562,
    "word": "efímera",
    "url": "https://lapalabradeldia.com/personalizada/?p=ZsOtbWVyYQ%3D%3D&t=true"
  },
  {
    "gameId": 561,
    "word": "cátodo",
    "url": "https://lapalabradeldia.com/personalizada/?p=w6F0b2Rv&t=true"
  },
  {
    "gameId": 560,
    "word": "tendón",
    "url": "https://lapalabradeldia.com/personalizada/?p=dGVuZMOzbg%3D%3D&t=true"
  },
  {
    "gameId": 559,
    "word": "táctica",
    "url": "https://lapalabradeldia.com/personalizada/?p=w6FjdGljYQ%3D%3D&t=true"
  },
  {
    "gameId": 558,
    "word": "enésima",
    "url": "https://lapalabradeldia.com/personalizada/?p=bsOpc2ltYQ%3D%3D&t=true"
  },
  {
    "gameId": 557,
    "word": "trítono",
    "url": "https://lapalabradeldia.com/personalizada/?p=dHLDrXRvbm8%3D&t=true"
  },
  {
    "gameId": 556,
    "word": "ácida",
    "url": "https://lapalabradeldia.com/personalizada/?p=w6FjaWRh&t=true"
  },
  {
    "gameId": 555,
    "word": "amónico",
    "url": "https://lapalabradeldia.com/personalizada/?p=YW3Ds25pY28%3D&t=true"
  },
  {
    "gameId": 554,
    "word": "lábil",
    "url": "https://lapalabradeldia.com/personalizada/?p=bMOhYmls&t=true"
  },
  {
    "gameId": 553,
    "word": "bíblica",
    "url": "https://lapalabradeldia.com/personalizada/?p=YsOtYmxpY2E%3D&t=true"
  },
  {
    "gameId": 552,
    "word": "árida",
    "url": "https://lapalabradeldia.com/personalizada/?p=w6FyaWRh&t=true"
  },
  {
    "gameId": 551,
    "word": "títere",
    "url": "https://lapalabradeldia.com/personalizada/?p=dMOtdGVyZQ%3D%3D&t=true"
  },
  {
    "gameId": 550,
    "word": "lírico",
    "url": "https://lapalabradeldia.com/personalizada/?p=w61yaWNv&t=true"
  },
  {
    "gameId": 549,
    "word": "álgido",
    "url": "https://lapalabradeldia.com/personalizada/?p=w6FsZ2lkbw%3D%3D&t=true"
  },
  {
    "gameId": 548,
    "word": "aérea",
    "url": "https://lapalabradeldia.com/personalizada/?p=YcOpcmVh&t=true"
  },
  {
    "gameId": 547,
    "word": "ídolo",
    "url": "https://lapalabradeldia.com/personalizada/?p=w61kb2xv&t=true"
  },
  {
    "gameId": 546,
    "word": "espía",
    "url": "https://lapalabradeldia.com/personalizada/?p=ZXNww61h&t=true"
  },
  {
    "gameId": 545,
    "word": "mérida",
    "url": "https://lapalabradeldia.com/personalizada/?p=bcOpcmlkYQ%3D%3D&t=true"
  },
  {
    "gameId": 544,
    "word": "fúlgida",
    "url": "https://lapalabradeldia.com/personalizada/?p=ZsO6bGdpZGE%3D&t=true"
  },
  {
    "gameId": 543,
    "word": "bahía",
    "url": "https://lapalabradeldia.com/personalizada/?p=YmFow61h&t=true"
  },
  {
    "gameId": 542,
    "word": "cónico",
    "url": "https://lapalabradeldia.com/personalizada/?p=Y8Ozbmljbw%3D%3D&t=true"
  },
  {
    "gameId": 541,
    "word": "plétora",
    "url": "https://lapalabradeldia.com/personalizada/?p=cGzDqXRvcmE%3D&t=true"
  },
  {
    "gameId": 540,
    "word": "glotón",
    "url": "https://lapalabradeldia.com/personalizada/?p=Z2xvdMOzbg%3D%3D&t=true"
  },
  {
    "gameId": 539,
    "word": "renglón",
    "url": "https://lapalabradeldia.com/personalizada/?p=cmVuZ2zDs24%3D&t=true"
  },
  {
    "gameId": 538,
    "word": "colofón",
    "url": "https://lapalabradeldia.com/personalizada/?p=Y29sb2bDs24%3D&t=true"
  },
  {
    "gameId": 537,
    "word": "férrico",
    "url": "https://lapalabradeldia.com/personalizada/?p=ZsOpcnJpY28%3D&t=true"
  },
  {
    "gameId": 536,
    "word": "flébil",
    "url": "https://lapalabradeldia.com/personalizada/?p=ZmzDqWJpbA%3D%3D&t=true"
  },
  {
    "gameId": 535,
    "word": "típico",
    "url": "https://lapalabradeldia.com/personalizada/?p=dMOtcGljbw%3D%3D&t=true"
  },
  {
    "gameId": 534,
    "word": "crónico",
    "url": "https://lapalabradeldia.com/personalizada/?p=Y3LDs25pY28%3D&t=true"
  },
  {
    "gameId": 533,
    "word": "víscera",
    "url": "https://lapalabradeldia.com/personalizada/?p=dsOtc2NlcmE%3D&t=true"
  },
  {
    "gameId": 532,
    "word": "gurú",
    "url": ""
  },
  {
    "gameId": 531,
    "word": "séquito",
    "url": "https://lapalabradeldia.com/personalizada/?p=c8OpcXVpdG8%3D&t=true"
  },
  {
    "gameId": 530,
    "word": "trébol",
    "url": "https://lapalabradeldia.com/personalizada/?p=dHLDqWJvbA%3D%3D&t=true"
  },
  {
    "gameId": 529,
    "word": "clínico",
    "url": "https://lapalabradeldia.com/personalizada/?p=Y2zDrW5pY28%3D&t=true"
  },
  {
    "gameId": 528,
    "word": "quemón",
    "url": "https://lapalabradeldia.com/personalizada/?p=cXVlbcOzbg%3D%3D&t=true"
  },
  {
    "gameId": 527,
    "word": "álgida",
    "url": "https://lapalabradeldia.com/personalizada/?p=w6FsZ2lkYQ%3D%3D&t=true"
  },
  {
    "gameId": 526,
    "word": "argón",
    "url": "https://lapalabradeldia.com/personalizada/?p=YXJnw7Nu&t=true"
  },
  {
    "gameId": 525,
    "word": "sílaba",
    "url": "https://lapalabradeldia.com/personalizada/?p=c8OtbGFiYQ%3D%3D&t=true"
  },
  {
    "gameId": 524,
    "word": "décima",
    "url": "https://lapalabradeldia.com/personalizada/?p=ZMOpY2ltYQ%3D%3D&t=true"
  },
  {
    "gameId": 523,
    "word": "oración",
    "url": "https://lapalabradeldia.com/personalizada/?p=b3JhY2nDs24%3D&t=true"
  },
  {
    "gameId": 522,
    "word": "sólido",
    "url": "https://lapalabradeldia.com/personalizada/?p=c8OzbGlkbw%3D%3D&t=true"
  },
  {
    "gameId": 521,
    "word": "alógena",
    "url": "https://lapalabradeldia.com/personalizada/?p=YWzDs2dlbmE%3D&t=true"
  },
  {
    "gameId": 520,
    "word": "imán",
    "url": ""
  },
  {
    "gameId": 519,
    "word": "perdón",
    "url": "https://lapalabradeldia.com/personalizada/?p=cGVyZMOzbg%3D%3D&t=true"
  },
  {
    "gameId": 518,
    "word": "cíclope",
    "url": "https://lapalabradeldia.com/personalizada/?p=Y8OtY2xvcGU%3D&t=true"
  },
  {
    "gameId": 517,
    "word": "café",
    "url": ""
  },
  {
    "gameId": 516,
    "word": "umbrío",
    "url": "https://lapalabradeldia.com/personalizada/?p=dW1icsOtbw%3D%3D&t=true"
  },
  {
    "gameId": 515,
    "word": "póster",
    "url": "https://lapalabradeldia.com/personalizada/?p=cMOzc3Rlcg%3D%3D&t=true"
  },
  {
    "gameId": 514,
    "word": "óseo",
    "url": ""
  },
  {
    "gameId": 513,
    "word": "vástago",
    "url": "https://lapalabradeldia.com/personalizada/?p=dsOhc3RhZ28%3D&t=true"
  },
  {
    "gameId": 512,
    "word": "jubón",
    "url": "https://lapalabradeldia.com/personalizada/?p=anViw7Nu&t=true"
  },
  {
    "gameId": 511,
    "word": "doblón",
    "url": "https://lapalabradeldia.com/personalizada/?p=ZG9ibMOzbg%3D%3D&t=true"
  },
  {
    "gameId": 510,
    "word": "bélica",
    "url": "https://lapalabradeldia.com/personalizada/?p=YsOpbGljYQ%3D%3D&t=true"
  },
  {
    "gameId": 509,
    "word": "génesis",
    "url": "https://lapalabradeldia.com/personalizada/?p=Z8OpbmVzaXM%3D&t=true"
  },
  {
    "gameId": 508,
    "word": "sofocón",
    "url": "https://lapalabradeldia.com/personalizada/?p=c29mb2PDs24%3D&t=true"
  },
  {
    "gameId": 507,
    "word": "bebé",
    "url": ""
  },
  {
    "gameId": 506,
    "word": "gánster",
    "url": "https://lapalabradeldia.com/personalizada/?p=Z8OhbnN0ZXI%3D&t=true"
  },
  {
    "gameId": 505,
    "word": "méndigo",
    "url": "https://lapalabradeldia.com/personalizada/?p=bcOpbmRpZ28%3D&t=true"
  },
  {
    "gameId": 504,
    "word": "ateísta",
    "url": "https://lapalabradeldia.com/personalizada/?p=YXRlw61zdGE%3D&t=true"
  },
  {
    "gameId": 503,
    "word": "óptica",
    "url": "https://lapalabradeldia.com/personalizada/?p=w7NwdGljYQ%3D%3D&t=true"
  },
  {
    "gameId": 502,
    "word": "ácueo",
    "url": "https://lapalabradeldia.com/personalizada/?p=w6FjdWVv&t=true"
  },
  {
    "gameId": 501,
    "word": "ígneo",
    "url": "https://lapalabradeldia.com/personalizada/?p=w61nbmVv&t=true"
  },
  {
    "gameId": 500,
    "word": "déspota",
    "url": "https://lapalabradeldia.com/personalizada/?p=ZMOpc3BvdGE%3D&t=true"
  },
  {
    "gameId": 499,
    "word": "ecóloga",
    "url": "https://lapalabradeldia.com/personalizada/?p=ZWPDs2xvZ2E%3D&t=true"
  },
  {
    "gameId": 498,
    "word": "anímico",
    "url": "https://lapalabradeldia.com/personalizada/?p=YW7DrW1pY28%3D&t=true"
  },
  {
    "gameId": 497,
    "word": "desván",
    "url": "https://lapalabradeldia.com/personalizada/?p=ZGVzdsOhbg%3D%3D&t=true"
  },
  {
    "gameId": 496,
    "word": "anímica",
    "url": "https://lapalabradeldia.com/personalizada/?p=YW7DrW1pY2E%3D&t=true"
  },
  {
    "gameId": 495,
    "word": "etílica",
    "url": "https://lapalabradeldia.com/personalizada/?p=ZXTDrWxpY2E%3D&t=true"
  },
  {
    "gameId": 494,
    "word": "óptimo",
    "url": "https://lapalabradeldia.com/personalizada/?p=cHRpbW8%3D&t=true"
  },
  {
    "gameId": 493,
    "word": "adiós",
    "url": "https://lapalabradeldia.com/personalizada/?p=YWRpw7Nz&t=true"
  },
  {
    "gameId": 492,
    "word": "atóxico",
    "url": "https://lapalabradeldia.com/personalizada/?p=YXTDs3hpY28%3D&t=true"
  },
  {
    "gameId": 491,
    "word": "táctico",
    "url": "https://lapalabradeldia.com/personalizada/?p=dMOhY3RpY28%3D&t=true"
  },
  {
    "gameId": 490,
    "word": "críquet",
    "url": "https://lapalabradeldia.com/personalizada/?p=Y3LDrXF1ZXQ%3D&t=true"
  },
  {
    "gameId": 489,
    "word": "tampón",
    "url": "https://lapalabradeldia.com/personalizada/?p=dGFtcMOzbg%3D%3D&t=true"
  },
  {
    "gameId": 488,
    "word": "rústica",
    "url": "https://lapalabradeldia.com/personalizada/?p=csO6c3RpY2E%3D&t=true"
  },
  {
    "gameId": 487,
    "word": "faltón",
    "url": "https://lapalabradeldia.com/personalizada/?p=ZmFsdMOzbg%3D%3D&t=true"
  },
  {
    "gameId": 486,
    "word": "bengalí",
    "url": "https://lapalabradeldia.com/personalizada/?p=YmVuZ2Fsw60%3D&t=true"
  },
  {
    "gameId": 485,
    "word": "polizón",
    "url": "https://lapalabradeldia.com/personalizada/?p=cG9saXrDs24%3D&t=true"
  },
  {
    "gameId": 484,
    "word": "buzón",
    "url": "https://lapalabradeldia.com/personalizada/?p=YnV6w7Nu&t=true"
  },
  {
    "gameId": 483,
    "word": "lirón",
    "url": "https://lapalabradeldia.com/personalizada/?p=bGlyw7Nu&t=true"
  },
  {
    "gameId": 482,
    "word": "cálao",
    "url": "https://lapalabradeldia.com/personalizada/?p=Y8OhbGFv&t=true"
  },
  {
    "gameId": 481,
    "word": "iraquí",
    "url": "https://lapalabradeldia.com/personalizada/?p=aXJhcXXDrQ%3D%3D&t=true"
  },
  {
    "gameId": 480,
    "word": "sátira",
    "url": "https://lapalabradeldia.com/personalizada/?p=c8OhdGlyYQ%3D%3D&t=true"
  },
  {
    "gameId": 479,
    "word": "abejón",
    "url": "https://lapalabradeldia.com/personalizada/?p=YWJlasOzbg%3D%3D&t=true"
  },
  {
    "gameId": 478,
    "word": "píldora",
    "url": "https://lapalabradeldia.com/personalizada/?p=cMOtbGRvcmE%3D&t=true"
  },
  {
    "gameId": 477,
    "word": "bífido",
    "url": "https://lapalabradeldia.com/personalizada/?p=YsOtZmlkbw%3D%3D&t=true"
  },
  {
    "gameId": 476,
    "word": "frenesí",
    "url": "https://lapalabradeldia.com/personalizada/?p=ZnJlbmVzw60%3D&t=true"
  },
  {
    "gameId": 475,
    "word": "póstuma",
    "url": "https://lapalabradeldia.com/personalizada/?p=cMOzc3R1bWE%3D&t=true"
  },
  {
    "gameId": 474,
    "word": "árbol",
    "url": "https://lapalabradeldia.com/personalizada/?p=w6FyYm9s&t=true"
  },
  {
    "gameId": 473,
    "word": "lúcido",
    "url": "https://lapalabradeldia.com/personalizada/?p=bMO6Y2lkbw%3D%3D&t=true"
  },
  {
    "gameId": 472,
    "word": "rígida",
    "url": "https://lapalabradeldia.com/personalizada/?p=csOtZ2lkYQ%3D%3D&t=true"
  },
  {
    "gameId": 471,
    "word": "cartón",
    "url": "https://lapalabradeldia.com/personalizada/?p=Y2FydMOzbg%3D%3D&t=true"
  },
  {
    "gameId": 470,
    "word": "cráneo",
    "url": "https://lapalabradeldia.com/personalizada/?p=Y3LDoW5lbw%3D%3D&t=true"
  },
  {
    "gameId": 469,
    "word": "campeón",
    "url": "https://lapalabradeldia.com/personalizada/?p=Y2FtcGXDs24%3D&t=true"
  },
  {
    "gameId": 468,
    "word": "bambú",
    "url": "https://lapalabradeldia.com/personalizada/?p=YmFtYsO6&t=true"
  },
  {
    "gameId": 467,
    "word": "desdén",
    "url": "https://lapalabradeldia.com/personalizada/?p=ZGVzZMOpbg%3D%3D&t=true"
  },
  {
    "gameId": 466,
    "word": "maniquí",
    "url": "https://lapalabradeldia.com/personalizada/?p=bWFuaXF1w60%3D&t=true"
  },
  {
    "gameId": 465,
    "word": "sequía",
    "url": "https://lapalabradeldia.com/personalizada/?p=c2VxdcOtYQ%3D%3D&t=true"
  },
  {
    "gameId": 464,
    "word": "épico",
    "url": "https://lapalabradeldia.com/personalizada/?p=w6lwaWNv&t=true"
  },
  {
    "gameId": 463,
    "word": "joyería",
    "url": "https://lapalabradeldia.com/personalizada/?p=am95ZXLDrWE%3D&t=true"
  },
  {
    "gameId": 462,
    "word": "válida",
    "url": "https://lapalabradeldia.com/personalizada/?p=dsOhbGlkYQ%3D%3D&t=true"
  },
  {
    "gameId": 461,
    "word": "pública",
    "url": "https://lapalabradeldia.com/personalizada/?p=cMO6YmxpY2E%3D&t=true"
  },
  {
    "gameId": 460,
    "word": "cetáceo",
    "url": "https://lapalabradeldia.com/personalizada/?p=Y2V0w6FjZW8%3D&t=true"
  },
  {
    "gameId": 459,
    "word": "mísera",
    "url": "https://lapalabradeldia.com/personalizada/?p=bcOtc2VyYQ%3D%3D&t=true"
  },
  {
    "gameId": 458,
    "word": "etílico",
    "url": "https://lapalabradeldia.com/personalizada/?p=ZXTDrWxpY28%3D&t=true"
  },
  {
    "gameId": 457,
    "word": "bóxer",
    "url": "https://lapalabradeldia.com/personalizada/?p=YsOzeGVy&t=true"
  },
  {
    "gameId": 456,
    "word": "róbalo",
    "url": "https://lapalabradeldia.com/personalizada/?p=csOzYmFsbw%3D%3D&t=true"
  },
  {
    "gameId": 455,
    "word": "látex",
    "url": "https://lapalabradeldia.com/personalizada/?p=bMOhdGV4&t=true"
  },
  {
    "gameId": 454,
    "word": "tesón",
    "url": "https://lapalabradeldia.com/personalizada/?p=dGVzw7Nu&t=true"
  },
  {
    "gameId": 453,
    "word": "besucón",
    "url": "https://lapalabradeldia.com/personalizada/?p=YmVzdWPDs24%3D&t=true"
  },
  {
    "gameId": 452,
    "word": "zoóloga",
    "url": "https://lapalabradeldia.com/personalizada/?p=em%2FDs2xvZ2E%3D&t=true"
  },
  {
    "gameId": 451,
    "word": "nórdico",
    "url": "https://lapalabradeldia.com/personalizada/?p=bsOzcmRpY28%3D&t=true"
  },
  {
    "gameId": 450,
    "word": "método",
    "url": "https://lapalabradeldia.com/personalizada/?p=bcOpdG9kbw%3D%3D&t=true"
  },
  {
    "gameId": 449,
    "word": "régimen",
    "url": "https://lapalabradeldia.com/personalizada/?p=csOpZ2ltZW4%3D&t=true"
  },
  {
    "gameId": 448,
    "word": "balcón",
    "url": "https://lapalabradeldia.com/personalizada/?p=YmFsY8Ozbg%3D%3D&t=true"
  },
  {
    "gameId": 447,
    "word": "también",
    "url": "https://lapalabradeldia.com/personalizada/?p=dGFtYmnDqW4%3D&t=true"
  },
  {
    "gameId": 446,
    "word": "uróloga",
    "url": "https://lapalabradeldia.com/personalizada/?p=dXLDs2xvZ2E%3D&t=true"
  },
  {
    "gameId": 445,
    "word": "rúbrica",
    "url": "https://lapalabradeldia.com/personalizada/?p=csO6YnJpY2E%3D&t=true"
  },
  {
    "gameId": 444,
    "word": "mástil",
    "url": "https://lapalabradeldia.com/personalizada/?p=bcOhc3RpbA%3D%3D&t=true"
  },
  {
    "gameId": 443,
    "word": "sádica",
    "url": "https://lapalabradeldia.com/personalizada/?p=c8OhZGljYQ%3D%3D&t=true"
  },
  {
    "gameId": 442,
    "word": "índice",
    "url": "https://lapalabradeldia.com/personalizada/?p=w61uZGljZQ%3D%3D&t=true"
  },
  {
    "gameId": 441,
    "word": "tónico",
    "url": "https://lapalabradeldia.com/personalizada/?p=dMOzbmljbw%3D%3D&t=true"
  },
  {
    "gameId": 440,
    "word": "cérvix",
    "url": "https://lapalabradeldia.com/personalizada/?p=Y8OpcnZpeA%3D%3D&t=true"
  },
  {
    "gameId": 439,
    "word": "dobló",
    "url": "https://lapalabradeldia.com/personalizada/?p=ZG9ibMOz&t=true"
  },
  {
    "gameId": 438,
    "word": "pelotón",
    "url": "https://lapalabradeldia.com/personalizada/?p=cGVsb3TDs24%3D&t=true"
  },
  {
    "gameId": 437,
    "word": "levitó",
    "url": "https://lapalabradeldia.com/personalizada/?p=bGV2aXTDsw%3D%3D&t=true"
  },
  {
    "gameId": 436,
    "word": "élite",
    "url": "https://lapalabradeldia.com/personalizada/?p=w6lsaXRl&t=true"
  },
  {
    "gameId": 435,
    "word": "tragón",
    "url": "https://lapalabradeldia.com/personalizada/?p=dHJhZ8Ozbg%3D%3D&t=true"
  },
  {
    "gameId": 434,
    "word": "prófuga",
    "url": "https://lapalabradeldia.com/personalizada/?p=cHLDs2Z1Z2E%3D&t=true"
  },
  {
    "gameId": 433,
    "word": "huésped",
    "url": "https://lapalabradeldia.com/personalizada/?p=aHXDqXNwZWQ%3D&t=true"
  },
  {
    "gameId": 432,
    "word": "láser",
    "url": "https://lapalabradeldia.com/personalizada/?p=bMOhc2Vy&t=true"
  },
  {
    "gameId": 431,
    "word": "antepié",
    "url": "https://lapalabradeldia.com/personalizada/?p=YW50ZXBpw6k%3D&t=true"
  },
  {
    "gameId": 430,
    "word": "erróneo",
    "url": "https://lapalabradeldia.com/personalizada/?p=ZXJyw7NuZW8%3D&t=true"
  },
  {
    "gameId": 429,
    "word": "médula",
    "url": "https://lapalabradeldia.com/personalizada/?p=bcOpZHVsYQ%3D%3D&t=true"
  },
  {
    "gameId": 428,
    "word": "ilícito",
    "url": "https://lapalabradeldia.com/personalizada/?p=aWzDrWNpdG8%3D&t=true"
  },
  {
    "gameId": 427,
    "word": "cálida",
    "url": "https://lapalabradeldia.com/personalizada/?p=Y8OhbGlkYQ%3D%3D&t=true"
  },
  {
    "gameId": 426,
    "word": "página",
    "url": "https://lapalabradeldia.com/personalizada/?p=cMOhZ2luYQ%3D%3D&t=true"
  },
  {
    "gameId": 425,
    "word": "pasión",
    "url": "https://lapalabradeldia.com/personalizada/?p=cGFzacOzbg%3D%3D&t=true"
  },
  {
    "gameId": 424,
    "word": "límbico",
    "url": "https://lapalabradeldia.com/personalizada/?p=bMOtbWJpY28%3D&t=true"
  },
  {
    "gameId": 423,
    "word": "víctima",
    "url": "https://lapalabradeldia.com/personalizada/?p=dsOtY3RpbWE%3D&t=true"
  },
  {
    "gameId": 422,
    "word": "volcán",
    "url": "https://lapalabradeldia.com/personalizada/?p=dm9sY8Ohbg%3D%3D&t=true"
  },
  {
    "gameId": 421,
    "word": "latió",
    "url": "https://lapalabradeldia.com/personalizada/?p=bGF0acOz&t=true"
  },
  {
    "gameId": 420,
    "word": "áureo",
    "url": "https://lapalabradeldia.com/personalizada/?p=w6F1cmVv&t=true"
  },
  {
    "gameId": 419,
    "word": "mármol",
    "url": "https://lapalabradeldia.com/personalizada/?p=bcOhcm1vbA%3D%3D&t=true"
  },
  {
    "gameId": 418,
    "word": "brócoli",
    "url": "https://lapalabradeldia.com/personalizada/?p=YnLDs2NvbGk%3D&t=true"
  },
  {
    "gameId": 417,
    "word": "flúor",
    "url": "https://lapalabradeldia.com/personalizada/?p=ZmzDum9y&t=true"
  },
  {
    "gameId": 416,
    "word": "fortín",
    "url": "https://lapalabradeldia.com/personalizada/?p=Zm9ydMOtbg%3D%3D&t=true"
  },
  {
    "gameId": 415,
    "word": "cocinó",
    "url": "https://lapalabradeldia.com/personalizada/?p=Y29jaW7Dsw%3D%3D&t=true"
  },
  {
    "gameId": 414,
    "word": "vándalo",
    "url": "https://lapalabradeldia.com/personalizada/?p=dsOhbmRhbG8%3D&t=true"
  },
  {
    "gameId": 413,
    "word": "mezcló",
    "url": "https://lapalabradeldia.com/personalizada/?p=bWV6Y2zDsw%3D%3D&t=true"
  },
  {
    "gameId": 412,
    "word": "poético",
    "url": "https://lapalabradeldia.com/personalizada/?p=cG%2FDqXRpY28%3D&t=true"
  },
  {
    "gameId": 411,
    "word": "crítica",
    "url": "https://lapalabradeldia.com/personalizada/?p=Y3LDrXRpY2E%3D&t=true"
  },
  {
    "gameId": 410,
    "word": "túnel",
    "url": "https://lapalabradeldia.com/personalizada/?p=dMO6bmVs&t=true"
  },
  {
    "gameId": 409,
    "word": "métrica",
    "url": "https://lapalabradeldia.com/personalizada/?p=bcOpdHJpY2E%3D&t=true"
  },
  {
    "gameId": 408,
    "word": "tórax",
    "url": "https://lapalabradeldia.com/personalizada/?p=dMOzcmF4&t=true"
  },
  {
    "gameId": 407,
    "word": "cúbica",
    "url": "https://lapalabradeldia.com/personalizada/?p=Y8O6YmljYQ%3D%3D&t=true"
  },
  {
    "gameId": 406,
    "word": "ilusión",
    "url": "https://lapalabradeldia.com/personalizada/?p=aWx1c2nDs24%3D&t=true"
  },
  {
    "gameId": 405,
    "word": "méxico",
    "url": "https://lapalabradeldia.com/personalizada/?p=bcOpeGljbw%3D%3D&t=true"
  },
  {
    "gameId": 404,
    "word": "burgués",
    "url": "https://lapalabradeldia.com/personalizada/?p=YnVyZ3XDqXM%3D&t=true"
  },
  {
    "gameId": 403,
    "word": "moción",
    "url": "https://lapalabradeldia.com/personalizada/?p=bW9jacOzbg%3D%3D&t=true"
  },
  {
    "gameId": 402,
    "word": "kárate",
    "url": "https://lapalabradeldia.com/personalizada/?p=a8OhcmF0ZQ%3D%3D&t=true"
  },
  {
    "gameId": 401,
    "word": "rábido",
    "url": "https://lapalabradeldia.com/personalizada/?p=csOhYmlkbw%3D%3D&t=true"
  },
  {
    "gameId": 400,
    "word": "lechón",
    "url": "https://lapalabradeldia.com/personalizada/?p=bGVjaMOzbg%3D%3D&t=true"
  },
  {
    "gameId": 399,
    "word": "eólica",
    "url": "https://lapalabradeldia.com/personalizada/?p=ZcOzbGljYQ%3D%3D&t=true"
  },
  {
    "gameId": 398,
    "word": "óptima",
    "url": "https://lapalabradeldia.com/personalizada/?p=w7NwdGltYQ%3D%3D&t=true"
  },
  {
    "gameId": 397,
    "word": "chupón",
    "url": "https://lapalabradeldia.com/personalizada/?p=Y2h1cMOzbg%3D%3D&t=true"
  },
  {
    "gameId": 396,
    "word": "hórrido",
    "url": "https://lapalabradeldia.com/personalizada/?p=aMOzcnJpZG8%3D&t=true"
  },
  {
    "gameId": 395,
    "word": "clásico",
    "url": "https://lapalabradeldia.com/personalizada/?p=Y2zDoXNpY28%3D&t=true"
  },
  {
    "gameId": 394,
    "word": "púlpito",
    "url": "https://lapalabradeldia.com/personalizada/?p=cMO6bHBpdG8%3D&t=true"
  },
  {
    "gameId": 393,
    "word": "nódulo",
    "url": "https://lapalabradeldia.com/personalizada/?p=bsOzZHVsbw%3D%3D&t=true"
  },
  {
    "gameId": 392,
    "word": "córner",
    "url": "https://lapalabradeldia.com/personalizada/?p=Y8Ozcm5lcg%3D%3D&t=true"
  },
  {
    "gameId": 391,
    "word": "delató",
    "url": "https://lapalabradeldia.com/personalizada/?p=ZGVsYXTDsw%3D%3D&t=true"
  },
  {
    "gameId": 390,
    "word": "bárbaro",
    "url": "https://lapalabradeldia.com/personalizada/?p=YsOhcmJhcm8%3D&t=true"
  },
  {
    "gameId": 389,
    "word": "pétalo",
    "url": "https://lapalabradeldia.com/personalizada/?p=cMOpdGFsbw%3D%3D&t=true"
  },
  {
    "gameId": 388,
    "word": "ovíparo",
    "url": "https://lapalabradeldia.com/personalizada/?p=b3bDrXBhcm8%3D&t=true"
  },
  {
    "gameId": 387,
    "word": "ámbito",
    "url": "https://lapalabradeldia.com/personalizada/?p=w6FtYml0bw%3D%3D&t=true"
  },
  {
    "gameId": 386,
    "word": "vómito",
    "url": "https://lapalabradeldia.com/personalizada/?p=dsOzbWl0bw%3D%3D&t=true"
  },
  {
    "gameId": 385,
    "word": "salmón",
    "url": "https://lapalabradeldia.com/personalizada/?p=c2FsbcOzbg%3D%3D&t=true"
  },
  {
    "gameId": 384,
    "word": "marrón",
    "url": "https://lapalabradeldia.com/personalizada/?p=bWFycsOzbg%3D%3D&t=true"
  },
  {
    "gameId": 383,
    "word": "fregón",
    "url": "https://lapalabradeldia.com/personalizada/?p=ZnJlZ8Ozbg%3D%3D&t=true"
  },
  {
    "gameId": 382,
    "word": "panzón",
    "url": "https://lapalabradeldia.com/personalizada/?p=cGFuesOzbg%3D%3D&t=true"
  },
  {
    "gameId": 381,
    "word": "trágico",
    "url": "https://lapalabradeldia.com/personalizada/?p=dHLDoWdpY28%3D&t=true"
  },
  {
    "gameId": 380,
    "word": "ártico",
    "url": "https://lapalabradeldia.com/personalizada/?p=w6FydGljbw%3D%3D&t=true"
  },
  {
    "gameId": 379,
    "word": "bisturí",
    "url": "https://lapalabradeldia.com/personalizada/?p=YmlzdHVyw60%3D&t=true"
  },
  {
    "gameId": 378,
    "word": "tríceps",
    "url": "https://lapalabradeldia.com/personalizada/?p=dHLDrWNlcHM%3D&t=true"
  },
  {
    "gameId": 377,
    "word": "anémica",
    "url": "https://lapalabradeldia.com/personalizada/?p=YW7DqW1pY2E%3D&t=true"
  },
  {
    "gameId": 376,
    "word": "etéreo",
    "url": "https://lapalabradeldia.com/personalizada/?p=ZXTDqXJlbw%3D%3D&t=true"
  },
  {
    "gameId": 375,
    "word": "túmulo",
    "url": "https://lapalabradeldia.com/personalizada/?p=dMO6bXVsbw%3D%3D&t=true"
  },
  {
    "gameId": 374,
    "word": "cíclico",
    "url": "https://lapalabradeldia.com/personalizada/?p=Y8OtY2xpY28%3D&t=true"
  },
  {
    "gameId": 373,
    "word": "sombrío",
    "url": "https://lapalabradeldia.com/personalizada/?p=c29tYnLDrW8%3D&t=true"
  },
  {
    "gameId": 372,
    "word": "aulló",
    "url": "https://lapalabradeldia.com/personalizada/?p=YXVsbMOz&t=true"
  },
  {
    "gameId": 371,
    "word": "montón",
    "url": "https://lapalabradeldia.com/personalizada/?p=bW9udMOzbg%3D%3D&t=true"
  },
  {
    "gameId": 370,
    "word": "cómica",
    "url": "https://lapalabradeldia.com/personalizada/?p=Y8OzbWljYQ%3D%3D&t=true"
  },
  {
    "gameId": 369,
    "word": "tóxico",
    "url": "https://lapalabradeldia.com/personalizada/?p=dMOzeGljbw%3D%3D&t=true"
  },
  {
    "gameId": 368,
    "word": "ardió",
    "url": "https://lapalabradeldia.com/personalizada/?p=YXJkacOz&t=true"
  },
  {
    "gameId": 367,
    "word": "desistí",
    "url": "https://lapalabradeldia.com/personalizada/?p=ZGVzaXN0w60%3D&t=true"
  },
  {
    "gameId": 366,
    "word": "dígito",
    "url": "https://lapalabradeldia.com/personalizada/?p=ZMOtZ2l0bw%3D%3D&t=true"
  },
  {
    "gameId": 365,
    "word": "furgón",
    "url": "https://lapalabradeldia.com/personalizada/?p=ZnVyZ8Ozbg%3D%3D&t=true"
  },
  {
    "gameId": 364,
    "word": "huracán",
    "url": "https://lapalabradeldia.com/personalizada/?p=aHVyYWPDoW4%3D&t=true"
  },
  {
    "gameId": 363,
    "word": "zepelín",
    "url": "https://lapalabradeldia.com/personalizada/?p=emVwZWzDrW4%3D&t=true"
  },
  {
    "gameId": 362,
    "word": "comodín",
    "url": "https://lapalabradeldia.com/personalizada/?p=Y29tb2TDrW4%3D&t=true"
  },
  {
    "gameId": 361,
    "word": "tímpano",
    "url": "https://lapalabradeldia.com/personalizada/?p=dMOtbXBhbm8%3D&t=true"
  },
  {
    "gameId": 360,
    "word": "gélida",
    "url": "https://lapalabradeldia.com/personalizada/?p=Z8OpbGlkYQ%3D%3D&t=true"
  },
  {
    "gameId": 359,
    "word": "canción",
    "url": "https://lapalabradeldia.com/personalizada/?p=Y2FuY2nDs24%3D&t=true"
  },
  {
    "gameId": 358,
    "word": "cortés",
    "url": "https://lapalabradeldia.com/personalizada/?p=Y29ydMOpcw%3D%3D&t=true"
  },
  {
    "gameId": 357,
    "word": "tostón",
    "url": "https://lapalabradeldia.com/personalizada/?p=dG9zdMOzbg%3D%3D&t=true"
  },
  {
    "gameId": 356,
    "word": "orégano",
    "url": "https://lapalabradeldia.com/personalizada/?p=b3LDqWdhbm8%3D&t=true"
  },
  {
    "gameId": 355,
    "word": "súbdito",
    "url": "https://lapalabradeldia.com/personalizada/?p=c8O6YmRpdG8%3D&t=true"
  },
  {
    "gameId": 354,
    "word": "azúcar",
    "url": "https://lapalabradeldia.com/personalizada/?p=YXrDumNhcg%3D%3D&t=true"
  },
  {
    "gameId": 353,
    "word": "maletín",
    "url": "https://lapalabradeldia.com/personalizada/?p=bWFsZXTDrW4%3D&t=true"
  },
  {
    "gameId": 352,
    "word": "sangró",
    "url": "https://lapalabradeldia.com/personalizada/?p=c2FuZ3LDsw%3D%3D&t=true"
  },
  {
    "gameId": 351,
    "word": "ímpetu",
    "url": "https://lapalabradeldia.com/personalizada/?p=w61tcGV0dQ%3D%3D&t=true"
  },
  {
    "gameId": 350,
    "word": "hámster",
    "url": "https://lapalabradeldia.com/personalizada/?p=aMOhbXN0ZXI%3D&t=true"
  },
  {
    "gameId": 349,
    "word": "básica",
    "url": "https://lapalabradeldia.com/personalizada/?p=YsOhc2ljYQ%3D%3D&t=true"
  },
  {
    "gameId": 348,
    "word": "órbita",
    "url": "https://lapalabradeldia.com/personalizada/?p=w7NyYml0YQ%3D%3D&t=true"
  },
  {
    "gameId": 347,
    "word": "dragón",
    "url": "https://lapalabradeldia.com/personalizada/?p=ZHJhZ8Ozbg%3D%3D&t=true"
  },
  {
    "gameId": 346,
    "word": "lógico",
    "url": "https://lapalabradeldia.com/personalizada/?p=bMOzZ2ljbw%3D%3D&t=true"
  },
  {
    "gameId": 345,
    "word": "irónica",
    "url": "https://lapalabradeldia.com/personalizada/?p=aXLDs25pY2E%3D&t=true"
  },
  {
    "gameId": 344,
    "word": "elevó",
    "url": "https://lapalabradeldia.com/personalizada/?p=ZWxldsOz&t=true"
  },
  {
    "gameId": 343,
    "word": "champú",
    "url": "https://lapalabradeldia.com/personalizada/?p=Y2hhbXDDug%3D%3D&t=true"
  },
  {
    "gameId": 342,
    "word": "agonizó",
    "url": "https://lapalabradeldia.com/personalizada/?p=YWdvbml6w7M%3D&t=true"
  },
  {
    "gameId": 341,
    "word": "rayón",
    "url": "https://lapalabradeldia.com/personalizada/?p=cmF5w7Nu&t=true"
  },
  {
    "gameId": 340,
    "word": "cúpula",
    "url": "https://lapalabradeldia.com/personalizada/?p=Y8O6cHVsYQ%3D%3D&t=true"
  },
  {
    "gameId": 339,
    "word": "pívot",
    "url": "https://lapalabradeldia.com/personalizada/?p=cMOtdm90&t=true"
  },
  {
    "gameId": 338,
    "word": "plática",
    "url": "https://lapalabradeldia.com/personalizada/?p=cGzDoXRpY2E%3D&t=true"
  },
  {
    "gameId": 337,
    "word": "tranvía",
    "url": "https://lapalabradeldia.com/personalizada/?p=dHJhbnbDrWE%3D&t=true"
  },
  {
    "gameId": 336,
    "word": "náutica",
    "url": "https://lapalabradeldia.com/personalizada/?p=bsOhdXRpY2E%3D&t=true"
  },
  {
    "gameId": 335,
    "word": "bálsamo",
    "url": "https://lapalabradeldia.com/personalizada/?p=YsOhbHNhbW8%3D&t=true"
  },
  {
    "gameId": 334,
    "word": "cóctel",
    "url": "https://lapalabradeldia.com/personalizada/?p=Y8OzY3RlbA%3D%3D&t=true"
  },
  {
    "gameId": 333,
    "word": "bongó",
    "url": "https://lapalabradeldia.com/personalizada/?p=Ym9uZ8Oz&t=true"
  },
  {
    "gameId": 332,
    "word": "lúdico",
    "url": "https://lapalabradeldia.com/personalizada/?p=bMO6ZGljbw%3D%3D&t=true"
  },
  {
    "gameId": 331,
    "word": "análogo",
    "url": "https://lapalabradeldia.com/personalizada/?p=YW7DoWxvZ28%3D&t=true"
  },
  {
    "gameId": 330,
    "word": "hábitat",
    "url": "https://lapalabradeldia.com/personalizada/?p=aMOhYml0YXQ%3D&t=true"
  },
  {
    "gameId": 329,
    "word": "púbicos",
    "url": "https://lapalabradeldia.com/personalizada/?p=cMO6Ymljb3M%3D&t=true"
  },
  {
    "gameId": 328,
    "word": "oráculo",
    "url": "https://lapalabradeldia.com/personalizada/?p=b3LDoWN1bG8%3D&t=true"
  },
  {
    "gameId": 327,
    "word": "párvulo",
    "url": "https://lapalabradeldia.com/personalizada/?p=cMOhcnZ1bG8%3D&t=true"
  },
  {
    "gameId": 326,
    "word": "serafín",
    "url": "https://lapalabradeldia.com/personalizada/?p=c2VyYWbDrW4%3D&t=true"
  },
  {
    "gameId": 325,
    "word": "lícita",
    "url": "https://lapalabradeldia.com/personalizada/?p=bMOtY2l0YQ%3D%3D&t=true"
  },
  {
    "gameId": 324,
    "word": "millón",
    "url": "https://lapalabradeldia.com/personalizada/?p=bWlsbMOzbg%3D%3D&t=true"
  },
  {
    "gameId": 323,
    "word": "epílogo",
    "url": "https://lapalabradeldia.com/personalizada/?p=ZXDDrWxvZ28%3D&t=true"
  },
  {
    "gameId": 322,
    "word": "ladrón",
    "url": "https://lapalabradeldia.com/personalizada/?p=bGFkcsOzbg%3D%3D&t=true"
  },
  {
    "gameId": 321,
    "word": "lémur",
    "url": "https://lapalabradeldia.com/personalizada/?p=bMOpbXVy&t=true"
  },
  {
    "gameId": 320,
    "word": "gruñón",
    "url": "https://lapalabradeldia.com/personalizada/?p=Z3J1w7HDs24%3D&t=true"
  },
  {
    "gameId": 319,
    "word": "tótem",
    "url": "https://lapalabradeldia.com/personalizada/?p=dMOzdGVt&t=true"
  },
  {
    "gameId": 318,
    "word": "delfín",
    "url": "https://lapalabradeldia.com/personalizada/?p=ZGVsZsOtbg%3D%3D&t=true"
  },
  {
    "gameId": 317,
    "word": "sífilis",
    "url": "https://lapalabradeldia.com/personalizada/?p=c8OtZmlsaXM%3D&t=true"
  },
  {
    "gameId": 316,
    "word": "fúnebre",
    "url": "https://lapalabradeldia.com/personalizada/?p=ZsO6bmVicmU%3D&t=true"
  },
  {
    "gameId": 315,
    "word": "térmico",
    "url": "https://lapalabradeldia.com/personalizada/?p=dMOpcm1pY28%3D&t=true"
  },
  {
    "gameId": 314,
    "word": "almíbar",
    "url": "https://lapalabradeldia.com/personalizada/?p=YWxtw61iYXI%3D&t=true"
  },
  {
    "gameId": 313,
    "word": "idóneo",
    "url": "https://lapalabradeldia.com/personalizada/?p=aWTDs25lbw%3D%3D&t=true"
  },
  {
    "gameId": 312,
    "word": "canadá",
    "url": "https://lapalabradeldia.com/personalizada/?p=Y2FuYWTDoQ%3D%3D&t=true"
  },
  {
    "gameId": 311,
    "word": "mentón",
    "url": "https://lapalabradeldia.com/personalizada/?p=bWVudMOzbg%3D%3D&t=true"
  },
  {
    "gameId": 310,
    "word": "cáncer",
    "url": "https://lapalabradeldia.com/personalizada/?p=Y8OhbmNlcg%3D%3D&t=true"
  },
  {
    "gameId": 309,
    "word": "cadáver",
    "url": "https://lapalabradeldia.com/personalizada/?p=Y2Fkw6F2ZXI%3D&t=true"
  },
  {
    "gameId": 308,
    "word": "última",
    "url": "https://lapalabradeldia.com/personalizada/?p=w7psdGltYQ%3D%3D&t=true"
  },
  {
    "gameId": 307,
    "word": "nómina",
    "url": "https://lapalabradeldia.com/personalizada/?p=bsOzbWluYQ%3D%3D&t=true"
  },
  {
    "gameId": 306,
    "word": "aluvión",
    "url": "https://lapalabradeldia.com/personalizada/?p=YWx1dmnDs24%3D&t=true"
  },
  {
    "gameId": 305,
    "word": "ilógico",
    "url": "https://lapalabradeldia.com/personalizada/?p=aWzDs2dpY28%3D&t=true"
  },
  {
    "gameId": 304,
    "word": "gemía",
    "url": "https://lapalabradeldia.com/personalizada/?p=Z2Vtw61h&t=true"
  },
  {
    "gameId": 303,
    "word": "máxima",
    "url": "https://lapalabradeldia.com/personalizada/?p=bcOheGltYQ%3D%3D&t=true"
  },
  {
    "gameId": 302,
    "word": "relucía",
    "url": "https://lapalabradeldia.com/personalizada/?p=cmVsdWPDrWE%3D&t=true"
  },
  {
    "gameId": 301,
    "word": "séptimo",
    "url": "https://lapalabradeldia.com/personalizada/?p=c8OpcHRpbW8%3D&t=true"
  },
  {
    "gameId": 300,
    "word": "ángel",
    "url": "https://lapalabradeldia.com/personalizada/?p=w6FuZ2Vs&t=true"
  },
  {
    "gameId": 299,
    "word": "lección",
    "url": "https://lapalabradeldia.com/personalizada/?p=bGVjY2nDs24%3D&t=true"
  },
  {
    "gameId": 298,
    "word": "avícola",
    "url": "https://lapalabradeldia.com/personalizada/?p=YXbDrWNvbGE%3D&t=true"
  },
  {
    "gameId": 297,
    "word": "sesión",
    "url": "https://lapalabradeldia.com/personalizada/?p=c2VzacOzbg%3D%3D&t=true"
  },
  {
    "gameId": 296,
    "word": "óscar",
    "url": "https://lapalabradeldia.com/personalizada/?p=w7NzY2Fy&t=true"
  },
  {
    "gameId": 295,
    "word": "enfrió",
    "url": "https://lapalabradeldia.com/personalizada/?p=ZW5mcmnDsw%3D%3D&t=true"
  },
  {
    "gameId": 294,
    "word": "boletín",
    "url": "https://lapalabradeldia.com/personalizada/?p=Ym9sZXTDrW4%3D&t=true"
  },
  {
    "gameId": 293,
    "word": "pezón",
    "url": "https://lapalabradeldia.com/personalizada/?p=cGV6w7Nu&t=true"
  },
  {
    "gameId": 292,
    "word": "deísta",
    "url": "https://lapalabradeldia.com/personalizada/?p=ZGXDrXN0YQ%3D%3D&t=true"
  },
  {
    "gameId": 291,
    "word": "bufón",
    "url": "https://lapalabradeldia.com/personalizada/?p=YnVmw7Nu&t=true"
  },
  {
    "gameId": 290,
    "word": "léxico",
    "url": "https://lapalabradeldia.com/personalizada/?p=bMOpeGljbw%3D%3D&t=true"
  },
  {
    "gameId": 289,
    "word": "estrés",
    "url": "https://lapalabradeldia.com/personalizada/?p=ZXN0csOpcw%3D%3D&t=true"
  },
  {
    "gameId": 288,
    "word": "pálida",
    "url": "https://lapalabradeldia.com/personalizada/?p=cMOhbGlkYQ%3D%3D&t=true"
  },
  {
    "gameId": 287,
    "word": "válvula",
    "url": "https://lapalabradeldia.com/personalizada/?p=dsOhbHZ1bGE%3D&t=true"
  },
  {
    "gameId": 286,
    "word": "jardín",
    "url": "https://lapalabradeldia.com/personalizada/?p=amFyZMOtbg%3D%3D&t=true"
  },
  {
    "gameId": 285,
    "word": "porción",
    "url": "https://lapalabradeldia.com/personalizada/?p=cG9yY2nDs24%3D&t=true"
  },
  {
    "gameId": 284,
    "word": "ámbar",
    "url": "https://lapalabradeldia.com/personalizada/?p=w6FtYmFy&t=true"
  },
  {
    "gameId": 283,
    "word": "paraíso",
    "url": "https://lapalabradeldia.com/personalizada/?p=cGFyYcOtc28%3D&t=true"
  },
  {
    "gameId": 282,
    "word": "atópico",
    "url": "https://lapalabradeldia.com/personalizada/?p=YXTDs3BpY28%3D&t=true"
  },
  {
    "gameId": 281,
    "word": "plácido",
    "url": "https://lapalabradeldia.com/personalizada/?p=cGzDoWNpZG8%3D&t=true"
  },
  {
    "gameId": 280,
    "word": "jónico",
    "url": "https://lapalabradeldia.com/personalizada/?p=asOzbmljbw%3D%3D&t=true"
  },
  {
    "gameId": 279,
    "word": "vibró",
    "url": "https://lapalabradeldia.com/personalizada/?p=dmlicsOz&t=true"
  },
  {
    "gameId": 278,
    "word": "vagón",
    "url": "https://lapalabradeldia.com/personalizada/?p=dmFnw7Nu&t=true"
  },
  {
    "gameId": 277,
    "word": "cédula",
    "url": "https://lapalabradeldia.com/personalizada/?p=Y8OpZHVsYQ%3D%3D&t=true"
  },
  {
    "gameId": 276,
    "word": "hábil",
    "url": "https://lapalabradeldia.com/personalizada/?p=aMOhYmls&t=true"
  },
  {
    "gameId": 275,
    "word": "páramo",
    "url": "https://lapalabradeldia.com/personalizada/?p=cOFyYW1v&t=true"
  },
  {
    "gameId": 274,
    "word": "quemó",
    "url": "https://lapalabradeldia.com/personalizada/?p=cXVlbfM%3D&t=true"
  },
  {
    "gameId": 273,
    "word": "andén",
    "url": "https://lapalabradeldia.com/personalizada/?p=YW5k6W4%3D&t=true"
  },
  {
    "gameId": 272,
    "word": "húmeda",
    "url": "https://lapalabradeldia.com/personalizada/?p=aPptZWRh&t=true"
  },
  {
    "gameId": 271,
    "word": "húmeda",
    "url": "https://lapalabradeldia.com/personalizada/?p=U2FsdGVkX1%2BXHXeeH%2FgeOcCCbJkwmvno2WEE9hDX7Co%3D&t=true"
  },
  {
    "gameId": 270,
    "word": "órgano",
    "url": "https://lapalabradeldia.com/personalizada/?p=U2FsdGVkX1%2F2NHZKenlAnrU5lFXcpy4in3e9ZNdKtVs%3D&t=true"
  },
  {
    "gameId": 269,
    "word": "inóculo",
    "url": "https://lapalabradeldia.com/personalizada/?p=U2FsdGVkX1%2BPzo76chElWA1Emgua%2B%2FJWH1jPx68eFNc%3D&t=true"
  },
  {
    "gameId": 268,
    "word": "módulo",
    "url": "https://lapalabradeldia.com/personalizada/?p=U2FsdGVkX1%2BgZ5Srn0jkALRzIjpnoMZ%2FZwAeq929Jao%3D&t=true"
  },
  {
    "gameId": 267,
    "word": "exótica",
    "url": "https://lapalabradeldia.com/personalizada/?p=U2FsdGVkX19QsepfTeyVgW0VNNGYDSyKdgI3beUuAYY%3D&t=true"
  },
  {
    "gameId": 266,
    "word": "fénix",
    "url": "https://lapalabradeldia.com/personalizada/?p=U2FsdGVkX1%2BOZOyd1TFzJro7ZWvPGkLnAxsLQiAcfmI%3D&t=true"
  },
  {
    "gameId": 265,
    "word": "lúcida",
    "url": "https://lapalabradeldia.com/personalizada/?p=U2FsdGVkX1%2BzCLBdZRrCHPZrkrWjSlK3OdKAQLlkWuM%3D&t=true"
  },
  {
    "gameId": 264,
    "word": "sótano",
    "url": "https://lapalabradeldia.com/personalizada/?p=U2FsdGVkX19LNhPx2qYDUQQTPmyqvjGEMn3%2BXLfGQl0%3D&t=true"
  },
  {
    "gameId": 263,
    "word": "jabalí",
    "url": "https://lapalabradeldia.com/personalizada/?p=U2FsdGVkX18yIbKtS867yodSkWeOVBiHUPE6an4zU%2B0%3D&t=true"
  },
  {
    "gameId": 262,
    "word": "trámite",
    "url": "https://lapalabradeldia.com/personalizada/?p=U2FsdGVkX1%2BXC8gp1tHJqFBXLQqCASdoZiBZ741aqVA%3D&t=true"
  },
  {
    "gameId": 261,
    "word": "bióloga",
    "url": "https://lapalabradeldia.com/personalizada/?p=U2FsdGVkX18m48ZV6lRsmJ7ckNb3LKYWdpoE4ssRW0s%3D&t=true"
  },
  {
    "gameId": 260,
    "word": "mártir",
    "url": "https://lapalabradeldia.com/personalizada/?p=U2FsdGVkX18TZ7kxOY%2FokE1B3UfpYuYYFpr3ZVwZ%2BHI%3D&t=true"
  },
  {
    "gameId": 259,
    "word": "canelón",
    "url": "https://lapalabradeldia.com/personalizada/?p=U2FsdGVkX1%2FQOhO5%2ByKkuZ1M%2Fbwx2OGuqZG%2BGAXGa3o%3D&t=true"
  },
  {
    "gameId": 258,
    "word": "alegría",
    "url": "https://lapalabradeldia.com/personalizada/?p=U2FsdGVkX196IMmLPW%2F5l4DYT%2FndJQSOwgDd3ypv6gY%3D&t=true"
  },
  {
    "gameId": 257,
    "word": "sésamo",
    "url": "https://lapalabradeldia.com/personalizada/?p=U2FsdGVkX1949SjUN91NIKx25b%2F1l%2F1JpawsbWzQC4w%3D&t=true"
  },
  {
    "gameId": 256,
    "word": "océano",
    "url": "https://lapalabradeldia.com/personalizada/?p=U2FsdGVkX1%2Fsp8O25eGOzMr4UUd0mhMEonddxtlxExY%3D&t=true"
  },
  {
    "gameId": 255,
    "word": "pícara",
    "url": "https://lapalabradeldia.com/personalizada/?p=U2FsdGVkX1%2FRWqoIpDxn%2B3r1IjRke4bkrt56SwRWNwo%3D&t=true"
  },
  {
    "gameId": 254,
    "word": "némesis",
    "url": "https://lapalabradeldia.com/personalizada/?p=U2FsdGVkX19vJZ7bdjvEMwpgA1Nd1SkZrEvcRQMGNfs%3D&t=true"
  },
  {
    "gameId": 253,
    "word": "póstumo",
    "url": "https://lapalabradeldia.com/personalizada/?p=U2FsdGVkX1%2BbWKvnKzSlVZoPEexChXLZKhBuQb8wLGE%3D&t=true"
  },
  {
    "gameId": 252,
    "word": "mágica",
    "url": "https://lapalabradeldia.com/personalizada/?p=U2FsdGVkX18I9B%2FBbrOwyS24U0mbVuUzoQJyVyMeP%2BY%3D&t=true"
  },
  {
    "gameId": 251,
    "word": "género",
    "url": "https://lapalabradeldia.com/personalizada/?p=U2FsdGVkX19LWy090JAeMuTTNFyhBTBKXJGdOxszXpI%3D&t=true"
  },
  {
    "gameId": 250,
    "word": "gráfico",
    "url": "https://lapalabradeldia.com/personalizada/?p=U2FsdGVkX1%2FoPX68DRYMzw99YQZwBI9BettgdsDvYWw%3D&t=true"
  },
  {
    "gameId": 249,
    "word": "iónica",
    "url": "https://lapalabradeldia.com/personalizada/?p=U2FsdGVkX19rTCx1EudCkJ7YAUTUB30Y4AQBP0zzIko%3D&t=true"
  },
  {
    "gameId": 248,
    "word": "líquido",
    "url": "https://lapalabradeldia.com/personalizada/?p=U2FsdGVkX1%2FUpLkWqdZ0h2Ri5PqMtBY63bb3GGVVgh4%3D&t=true"
  },
  {
    "gameId": 247,
    "word": "saudí",
    "url": "https://lapalabradeldia.com/personalizada/?p=U2FsdGVkX19HKdYdMrUeg0n1xQJGW6Ol3b%2BYSsP940Q%3D&t=true"
  },
  {
    "gameId": 246,
    "word": "víspera",
    "url": "https://lapalabradeldia.com/personalizada/?p=U2FsdGVkX19kjPGG78iYe8uQ%2BNHCu9iZ7Disvx%2BqTm4%3D&t=true"
  },
  {
    "gameId": 245,
    "word": "rítmica",
    "url": "https://lapalabradeldia.com/personalizada/?p=U2FsdGVkX1%2BAz4hB1YZ22fargZM5eYq5L4ZR6d4Z5gc%3D&t=true"
  },
  {
    "gameId": 244,
    "word": "húsar",
    "url": "https://lapalabradeldia.com/personalizada/?p=U2FsdGVkX19wYx3Hx4Qr8eS6qygI35V9iuVqOjCt%2BVc%3D&t=true"
  },
  {
    "gameId": 243,
    "word": "lírica",
    "url": "https://lapalabradeldia.com/personalizada/?p=U2FsdGVkX1%2FZ7Apa35g8RF%2FdJxBjqCZh87ntrDhHnc8%3D&t=true"
  },
  {
    "gameId": 242,
    "word": "bótox",
    "url": "https://lapalabradeldia.com/personalizada/?p=U2FsdGVkX18oVRI0Rl%2F273NCFfxbmn2XTHmCOW3OI4w%3D&t=true"
  },
  {
    "gameId": 241,
    "word": "vínculo",
    "url": "https://lapalabradeldia.com/personalizada/?p=U2FsdGVkX1%2BXpfi7QSXwIgiMce6ciJgq077lceXoURo%3D&t=true"
  },
  {
    "gameId": 240,
    "word": "párroco",
    "url": "https://lapalabradeldia.com/personalizada/?p=U2FsdGVkX1%2F91XL2GUcLZ0RlXTkl85XqJ3%2F0hOPAB5U%3D&t=true"
  },
  {
    "gameId": 239,
    "word": "anónima",
    "url": "https://lapalabradeldia.com/personalizada/?p=U2FsdGVkX1%2BL7g247M8Dcdeaf4bOMwLFcr5NcpqEIX8%3D&t=true"
  },
  {
    "gameId": 238,
    "word": "ciénaga",
    "url": "https://lapalabradeldia.com/personalizada/?p=U2FsdGVkX1%2BQy2ANmApfBDg9fUBqRoGrG5Hd1PQQXxQ%3D&t=true"
  },
  {
    "gameId": 237,
    "word": "energía",
    "url": "https://lapalabradeldia.com/personalizada/?p=U2FsdGVkX19Y74pgJDQfM8whO8wmPpeYb%2FKPBSjD0Uc%3D&t=true"
  },
  {
    "gameId": 236,
    "word": "inmóvil",
    "url": "https://lapalabradeldia.com/personalizada/?p=U2FsdGVkX1%2F1NBVNYV4S5ss8I0uXm26uicCzqfS30UM%3D&t=true"
  },
  {
    "gameId": 235,
    "word": "nítrico",
    "url": "https://lapalabradeldia.com/personalizada/?p=U2FsdGVkX188%2Fp1MrPp0qWPLAKL%2B%2FAHt9W7SC%2FY6tPM%3D&t=true"
  },
  {
    "gameId": 234,
    "word": "mímica",
    "url": "https://lapalabradeldia.com/personalizada/?p=U2FsdGVkX1%2F6lIQiiTMQsJ5g8u372zF3bTouIBC5LtE%3D&t=true"
  },
  {
    "gameId": 233,
    "word": "teórico",
    "url": "https://lapalabradeldia.com/personalizada/?p=U2FsdGVkX1%2BpZseQ1eQSBdC6DCRT8ABT85jdN%2BKW3lU%3D&t=true"
  },
  {
    "gameId": 232,
    "word": "cestón",
    "url": "https://lapalabradeldia.com/personalizada/?p=U2FsdGVkX18uaaajJxB3al%2BvBqKEj1bLr1sOweW5UtY%3D&t=true"
  },
  {
    "gameId": 231,
    "word": "llorón",
    "url": "https://lapalabradeldia.com/personalizada/?p=U2FsdGVkX19ZuhWtOhtYUf60FpVeb2m3Q9ynGsxhuB4%3D&t=true"
  },
  {
    "gameId": 230,
    "word": "báscula",
    "url": "https://lapalabradeldia.com/personalizada/?p=U2FsdGVkX1%2Bh%2BK6h3R%2BsZA8vf68yiinWmdVRfGb71U4%3D&t=true"
  },
  {
    "gameId": 229,
    "word": "varón",
    "url": "https://lapalabradeldia.com/personalizada/?p=U2FsdGVkX1%2FnCHGiU4yu6Q3EBc1HLxyNUnkuF4cuyD4%3D&t=true"
  },
  {
    "gameId": 228,
    "word": "víbora",
    "url": "https://lapalabradeldia.com/personalizada/?p=U2FsdGVkX18wKJAV5s94qNU0OkXEXXZvGSb55OhcxZw%3D&t=true"
  },
  {
    "gameId": 227,
    "word": "ataúd",
    "url": "https://lapalabradeldia.com/personalizada/?p=U2FsdGVkX19mozThDuulz8eR1hME7EkMjj%2F7ibQizQQ%3D&t=true"
  },
  {
    "gameId": 226,
    "word": "filtró",
    "url": "https://lapalabradeldia.com/personalizada/?p=U2FsdGVkX18T83%2B4EBy1Q3zHHbBo0l1sT7yRpHJawjE%3D&t=true"
  },
  {
    "gameId": 225,
    "word": "párpado",
    "url": "https://lapalabradeldia.com/personalizada/?p=U2FsdGVkX1%2FsHddMx2NlNnpOmhUI8yt8Zvgadg3uFMA%3D&t=true"
  },
  {
    "gameId": 224,
    "word": "ética",
    "url": "https://lapalabradeldia.com/personalizada/?p=U2FsdGVkX1%2BcJ%2FqLwRKkcrN18bJdqh%2FrzmcAKojtOwI%3D&t=true"
  },
  {
    "gameId": 223,
    "word": "cóndor",
    "url": "https://lapalabradeldia.com/personalizada/?p=U2FsdGVkX1%2BtABf4JOIhUrXlj2%2FJwvGuxRIP3XCsfS0%3D&t=true"
  },
  {
    "gameId": 222,
    "word": "pústula",
    "url": "https://lapalabradeldia.com/personalizada/?p=U2FsdGVkX18pBZ3dfAhnXOiQI%2BqSPdKqjGSx3ZrrZnc%3D&t=true"
  },
  {
    "gameId": 221,
    "word": "galería",
    "url": "https://lapalabradeldia.com/personalizada/?p=U2FsdGVkX18R7%2Bteb8uk%2BpREvh6O2BYIaMv7vRoCDTo%3D&t=true"
  },
  {
    "gameId": 220,
    "word": "indicó",
    "url": "https://lapalabradeldia.com/personalizada/?p=U2FsdGVkX1%2FoUfJj9kV3mKyttZ2u4ktsvPUDghg%2BAF0%3D&t=true"
  },
  {
    "gameId": 219,
    "word": "símbolo",
    "url": "https://lapalabradeldia.com/personalizada/?p=U2FsdGVkX1%2BsGHo%2FbuojV0MJ3aHvmoOkywSM5x7%2BjbI%3D&t=true"
  },
  {
    "gameId": 218,
    "word": "láctico",
    "url": "https://lapalabradeldia.com/personalizada/?p=U2FsdGVkX18NKWROzBy218wUHFvGbJsAT%2BEzMilHfBU%3D&t=true"
  },
  {
    "gameId": 217,
    "word": "clímax",
    "url": "https://lapalabradeldia.com/personalizada/?p=U2FsdGVkX18IqQqUpOtoVolo49tr7FwrMO1%2BNS6ZC58%3D&t=true"
  },
  {
    "gameId": 216,
    "word": "hélice",
    "url": "https://lapalabradeldia.com/personalizada/?p=U2FsdGVkX1%2FnTuM0th1VUdgz0FqkI%2B9siTupHFv6QnY%3D&t=true"
  },
  {
    "gameId": 215,
    "word": "maratón",
    "url": "https://lapalabradeldia.com/personalizada/?p=U2FsdGVkX187x6fUPWhcjqA8c1iIflwIs29AUtwgzuw%3D&t=true"
  },
  {
    "gameId": 214,
    "word": "cósmica",
    "url": "https://lapalabradeldia.com/personalizada/?p=U2FsdGVkX18OJWEcf1z9t0DDFeXlmbMKVS%2BhmVa5kfQ%3D&t=true"
  },
  {
    "gameId": 213,
    "word": "ración",
    "url": "https://lapalabradeldia.com/personalizada/?p=U2FsdGVkX1%2FvNYHpXEis6NNWV8iWouDNVe1ja1y2xFs%3D&t=true"
  },
  {
    "gameId": 212,
    "word": "noción",
    "url": "https://lapalabradeldia.com/personalizada/?p=U2FsdGVkX1%2F27uecz3ViMnPsfknBhPufDCZBzx1kBEY%3D&t=true"
  },
  {
    "gameId": 211,
    "word": "cólera",
    "url": "https://lapalabradeldia.com/personalizada/?p=U2FsdGVkX198pMFktVT5gCmPKfR4H9Kz5UIMV%2FBz3L4%3D&t=true"
  },
  {
    "gameId": 210,
    "word": "abolió",
    "url": "https://lapalabradeldia.com/personalizada/?p=U2FsdGVkX1%2BxbHrMfygTSEakFCNSHpYK1BQyIoykh%2Bo%3D&t=true"
  },
  {
    "gameId": 209,
    "word": "erótica",
    "url": "https://lapalabradeldia.com/personalizada/?p=U2FsdGVkX18j%2FWR7U2kTRy9pnn7Ym2xRfndVNLCUeNY%3D&t=true"
  },
  {
    "gameId": 208,
    "word": "sopló",
    "url": "https://lapalabradeldia.com/personalizada/?p=U2FsdGVkX1%2Fc8tYxy17waayoJD7jnXzcQ5qR8WrwYak%3D&t=true"
  },
  {
    "gameId": 207,
    "word": "pájaro",
    "url": "https://lapalabradeldia.com/personalizada/?p=U2FsdGVkX18nWJHZXI%2FbO5hvSUuwiFKwZU0k3T4y8bo%3D&t=true"
  },
  {
    "gameId": 206,
    "word": "sísmico",
    "url": "https://lapalabradeldia.com/personalizada/?p=U2FsdGVkX1%2BlpijdmuFoYEJjiNCurGlwfw6NZ4Fbn%2Bc%3D&t=true"
  },
  {
    "gameId": 205,
    "word": "patrón",
    "url": "https://lapalabradeldia.com/personalizada/?p=U2FsdGVkX18Dsij3UgYyg4Cp69G%2BM5yK0kaDQNhaArU%3D&t=true"
  },
  {
    "gameId": 204,
    "word": "común",
    "url": "https://lapalabradeldia.com/personalizada/?p=U2FsdGVkX18sLsRKMEdccqW722PWGHRM%2BGSX2Co1ELE%3D&t=true"
  },
  {
    "gameId": 203,
    "word": "glóbulo",
    "url": "https://lapalabradeldia.com/personalizada/?p=U2FsdGVkX18FMlbHZXFgQTcbnp%2BhAPesZX4gKapL0%2FA%3D&t=true"
  },
  {
    "gameId": 202,
    "word": "úrico",
    "url": "https://lapalabradeldia.com/personalizada/?p=U2FsdGVkX1%2BrMyiHtV5M0x6n4OIIt2gvb7tFH7vRoq8%3D&t=true"
  },
  {
    "gameId": 201,
    "word": "árbitro",
    "url": "https://lapalabradeldia.com/personalizada/?p=U2FsdGVkX1%2F%2BqRJmi5cXyWAEBH1rSqOYmFuCACMsLrw%3D&t=true"
  },
  {
    "gameId": 200,
    "word": "estría",
    "url": "https://lapalabradeldia.com/personalizada/?p=U2FsdGVkX18VSGXQMX5EPDT7pdqW8vC4cvcSPSgBns4%3D&t=true"
  },
  {
    "gameId": 199,
    "word": "mínima",
    "url": "https://lapalabradeldia.com/personalizada/?p=U2FsdGVkX18S5%2BGXOWN%2BS75l80Biy%2BLsdJGt393Q4T4%3D&t=true"
  },
  {
    "gameId": 198,
    "word": "fármaco",
    "url": "https://lapalabradeldia.com/personalizada/?p=U2FsdGVkX1%2F6cPp0HDsLldnUSAfXLl1Uad7Q7uVvCAo%3D&t=true"
  },
  {
    "gameId": 197,
    "word": "técnica",
    "url": "https://lapalabradeldia.com/personalizada/?p=U2FsdGVkX19knx%2B6ScDPIqnBaNdifGth%2BcMFDNLvXD0%3D&t=true"
  },
  {
    "gameId": 196,
    "word": "íntegra",
    "url": "https://lapalabradeldia.com/personalizada/?p=U2FsdGVkX1%2BXg%2FLFeb3x4EwdSqXxRr54JPsxK44ekFs%3D&t=true"
  },
  {
    "gameId": 195,
    "word": "óxido",
    "url": "https://lapalabradeldia.com/personalizada/?p=U2FsdGVkX1%2F77zhPQHiYZHGZRykPGNgKvS%2FjdajSmr8%3D&t=true"
  },
  {
    "gameId": 194,
    "word": "belén",
    "url": "https://lapalabradeldia.com/personalizada/?p=U2FsdGVkX19Yzg%2BNgLkePa4GVQSnCo2crPw1Ajwx81c%3D&t=true"
  },
  {
    "gameId": 193,
    "word": "fósil",
    "url": "https://lapalabradeldia.com/personalizada/?p=U2FsdGVkX1%2BrfEUgh4ZufrmpokvidkqElhMcfSIoCEQ%3D&t=true"
  },
  {
    "gameId": 192,
    "word": "roscón",
    "url": "https://lapalabradeldia.com/personalizada/?p=U2FsdGVkX1%2B%2BrW3nP3bFMYD4zf4S4403lO49%2BtJCbMs%3D&t=true"
  },
  {
    "gameId": 191,
    "word": "clínica",
    "url": "https://lapalabradeldia.com/personalizada/?p=U2FsdGVkX1%2BhaTnUHhtHVfE%2BUvBPId2EBeUfvr%2Bjrgs%3D&t=true"
  },
  {
    "gameId": 190,
    "word": "gónada",
    "url": "https://lapalabradeldia.com/personalizada/?p=U2FsdGVkX1%2FHUYE1KdDOuxBAgkha5vVPfn6OCPEqnIA%3D&t=true"
  },
  {
    "gameId": 189,
    "word": "camión",
    "url": "https://lapalabradeldia.com/personalizada/?p=U2FsdGVkX19QS%2Bxbk0vTORz8%2BZ8ONnsAY5BfSvUpXJo%3D&t=true"
  },
  {
    "gameId": 188,
    "word": "acólito",
    "url": "https://lapalabradeldia.com/personalizada/?p=U2FsdGVkX1%2F%2Fz5W1YDWHOLB3p7k9jZ0iaVUotHPhQKk%3D&t=true"
  },
  {
    "gameId": 187,
    "word": "crónica",
    "url": "https://lapalabradeldia.com/personalizada/?p=U2FsdGVkX1%2BAzTr3IgyxN55kOXr1mOae3%2FQP5oME99Y%3D&t=true"
  },
  {
    "gameId": 186,
    "word": "unánime",
    "url": "https://lapalabradeldia.com/personalizada/?p=U2FsdGVkX1%2FV2GoYH7CFDYB0NVIOavoi%2BON330X8iFk%3D&t=true"
  },
  {
    "gameId": 185,
    "word": "melón",
    "url": "https://lapalabradeldia.com/personalizada/?p=U2FsdGVkX19uAsaniJn5X5EFla58StBs19ybNDoc1mo%3D&t=true"
  },
  {
    "gameId": 184,
    "word": "máquina",
    "url": "https://lapalabradeldia.com/personalizada/?p=U2FsdGVkX1%2F5YUNeD2YgzQpA%2FINZuklavqp0BNYOMMA%3D&t=true"
  },
  {
    "gameId": 183,
    "word": "cantón",
    "url": "https://lapalabradeldia.com/personalizada/?p=U2FsdGVkX1%2FtA1Zeic%2Fij3F4IpJftRTijzV34WEhlmY%3D&t=true"
  },
  {
    "gameId": 182,
    "word": "báltico",
    "url": "https://lapalabradeldia.com/personalizada/?p=U2FsdGVkX18essZ%2B9JZDCEZn6IQQUAuDNEoDIJdWvJk%3D&t=true"
  },
  {
    "gameId": 181,
    "word": "índole",
    "url": "https://lapalabradeldia.com/personalizada/?p=U2FsdGVkX1%2FE8oB6BcII%2Fxqdl75c%2BhP9kqRxpbeqKKM%3D&t=true"
  },
  {
    "gameId": 180,
    "word": "cóclea",
    "url": "https://lapalabradeldia.com/personalizada/?p=U2FsdGVkX1%2BVskKSZOt%2FfDkuVkLSb%2FeD9U3KYDl8MKQ%3D&t=true"
  },
  {
    "gameId": 179,
    "word": "mística",
    "url": "https://lapalabradeldia.com/personalizada/?p=U2FsdGVkX1%2B7bxpyrJxIv2SYqwZ8gZ2UWIJeMri5H6M%3D&t=true"
  },
  {
    "gameId": 178,
    "word": "óptica",
    "url": "https://lapalabradeldia.com/personalizada/?p=U2FsdGVkX1%2B%2FlF17NNQZ7g%2Bfnz6f5bl9uJwrz0ryg1k%3D&t=true"
  },
  {
    "gameId": 177,
    "word": "biónico",
    "url": "https://lapalabradeldia.com/personalizada/?p=U2FsdGVkX1%2FP9hfX76yUQyT5uWGSrLvMUrE9yyg%2F9c0%3D&t=true"
  },
  {
    "gameId": 176,
    "word": "dulzón",
    "url": "https://lapalabradeldia.com/personalizada/?p=U2FsdGVkX1%2B844vWur9sTLsZoFTpGv7K1rOljmS195w%3D&t=true"
  },
  {
    "gameId": 175,
    "word": "síntoma",
    "url": "https://lapalabradeldia.com/personalizada/?p=U2FsdGVkX1%2Bhe4Y3l2vuoqAGTcVGCsMGsiYpxJsu7Gc%3D&t=true"
  },
  {
    "gameId": 174,
    "word": "bulería",
    "url": "https://lapalabradeldia.com/personalizada/?p=U2FsdGVkX1%2BNq7CB234HnDKjTDEfSwesptEZn%2F%2BAOvI%3D&t=true"
  },
  {
    "gameId": 173,
    "word": "unión",
    "url": "https://lapalabradeldia.com/personalizada/?p=U2FsdGVkX1%2FnwFug0ele2f4M0%2BIh1udDT97yfJvN3OI%3D&t=true"
  },
  {
    "gameId": 172,
    "word": "flácido",
    "url": "https://lapalabradeldia.com/personalizada/?p=U2FsdGVkX18d7T%2B4Bb5kjmtk9u7dlGB5aHKmWPn8M2Y%3D&t=true"
  },
  {
    "gameId": 171,
    "word": "pádel",
    "url": "https://lapalabradeldia.com/personalizada/?p=U2FsdGVkX187gX0655zmkjtmKJNEwwsAYnX%2FJrj7Vz0%3D&t=true"
  },
  {
    "gameId": 170,
    "word": "muñón",
    "url": "https://lapalabradeldia.com/personalizada/?p=U2FsdGVkX18VgXGWr6ljIasBXRgzd6DgS7RFPadXO34%3D&t=true"
  },
  {
    "gameId": 169,
    "word": "bípode",
    "url": "https://lapalabradeldia.com/personalizada/?p=U2FsdGVkX19P7zDZgotxURDWTU2w3zNp2i%2FZwfR39qo%3D&t=true"
  },
  {
    "gameId": 168,
    "word": "lámpara",
    "url": "https://lapalabradeldia.com/personalizada/?p=U2FsdGVkX19b9tXhyj9TN0NM16akvAqcIADnlMD6WWU%3D&t=true"
  },
  {
    "gameId": 167,
    "word": "cabezón",
    "url": "https://lapalabradeldia.com/personalizada/?p=U2FsdGVkX1%2BxlCu%2B70hw428rbpYG4%2BkDHb006t6pPtE%3D&t=true"
  },
  {
    "gameId": 166,
    "word": "frágil",
    "url": "https://lapalabradeldia.com/personalizada/?p=U2FsdGVkX1%2BSBj8N7CbAEEkCnVqpAT9Dua1HcgR5Eho%3D&t=true"
  },
  {
    "gameId": 165,
    "word": "bastión",
    "url": "https://lapalabradeldia.com/personalizada/?p=U2FsdGVkX19%2BO1U%2BfkpmpQWgZ1zMQWXmF6JpOgffHG4%3D&t=true"
  },
  {
    "gameId": 164,
    "word": "párrafo",
    "url": "https://lapalabradeldia.com/personalizada/?p=U2FsdGVkX19huyIqAgFNHj12GbwKN26ZeVox8ZLnCPQ%3D&t=true"
  },
  {
    "gameId": 163,
    "word": "tráquea",
    "url": "https://lapalabradeldia.com/personalizada/?p=U2FsdGVkX1%2BR9Cx5HWmDauUD8EhMB161j6Izwg24bMU%3D&t=true"
  },
  {
    "gameId": 162,
    "word": "rutina",
    "url": "https://lapalabradeldia.com/personalizada/?p=U2FsdGVkX1%2FeeTOmXrb%2Fc7So9jJsZNw%2Bus5X5n0Q6EQ%3D&t=false"
  },
  {
    "gameId": 161,
    "word": "afición",
    "url": "https://lapalabradeldia.com/personalizada/?p=U2FsdGVkX1%2B82%2Ftusz%2BD%2BxuRlrBq7fh7fXBowWjiAO4%3D&t=true"
  },
  {
    "gameId": 160,
    "word": "mérito",
    "url": "https://lapalabradeldia.com/personalizada/?p=U2FsdGVkX19z1Y3YWyTgXmxePbkU7wAUY2QTa6e2lrw%3D&t=true"
  },
  {
    "gameId": 159,
    "word": "maníaco",
    "url": "https://lapalabradeldia.com/personalizada/?p=U2FsdGVkX1%2F6TnDD%2BOB%2B7acjUsK9Pi22xBKqdLAtRjw%3D&t=true"
  },
  {
    "gameId": 158,
    "word": "músculo",
    "url": "https://lapalabradeldia.com/personalizada/?p=U2FsdGVkX1%2FGux7sosgK940WxcA1NFGWGg5WElM0VbU%3D&t=true"
  },
  {
    "gameId": 157,
    "word": "lástima",
    "url": "https://lapalabradeldia.com/personalizada/?p=U2FsdGVkX1%2BdBi7h0h72WpvksTNsE5Qp%2B6P07%2BBwgXc%3D&t=true"
  },
  {
    "gameId": 156,
    "word": "cirugía",
    "url": "https://lapalabradeldia.com/personalizada/?p=U2FsdGVkX1%2BjF8fsWs482NMw0hCrpOFYkAkGb8ytWNc%3D&t=true"
  },
  {
    "gameId": 155,
    "word": "cáliz",
    "url": "https://lapalabradeldia.com/personalizada/?p=U2FsdGVkX19Cm4CPAoyJWlxRff%2F5R6gJAPe3L7Wy%2FVE%3D&t=true"
  },
  {
    "gameId": 154,
    "word": "góndola",
    "url": "https://lapalabradeldia.com/personalizada/?p=U2FsdGVkX19yKs8g8Grkhc1X3RaRL34SnXNTOG2OHeg%3D&t=true"
  },
  {
    "gameId": 153,
    "word": "hirvió",
    "url": "https://lapalabradeldia.com/personalizada/?p=U2FsdGVkX19gilCNFLR%2F94aI5KBEwKFAAJoPU7allJo%3D&t=true"
  },
  {
    "gameId": 152,
    "word": "oxidó",
    "url": "https://lapalabradeldia.com/personalizada/?p=U2FsdGVkX1%2FxxBcFOurKxERxMCUUWbzQpgWfxyZi6tE%3D&t=true"
  },
  {
    "gameId": 151,
    "word": "cálculo",
    "url": "https://lapalabradeldia.com/personalizada/?p=U2FsdGVkX1%2BjMvb8LMzDNZDhNEpMnMBRqLFGEqR5uKA%3D&t=true"
  },
  {
    "gameId": 150,
    "word": "atómico",
    "url": "https://lapalabradeldia.com/personalizada/?p=U2FsdGVkX1%2B6KXgEqH5U1mGYTYL9PkGfwYTvdoDR958%3D&t=true"
  },
  {
    "gameId": 149,
    "word": "énfasis",
    "url": "https://lapalabradeldia.com/personalizada/?p=U2FsdGVkX18dZMthQORae1S0x3sB6I2sAfaIa9E5Kco%3D&t=true"
  },
  {
    "gameId": 148,
    "word": "máscara",
    "url": "https://lapalabradeldia.com/personalizada/?p=U2FsdGVkX18u0HEBRaz%2BuJ4ZLnG%2B0kvJORXDko%2FX7AM%3D&t=true"
  },
  {
    "gameId": 147,
    "word": "vermú",
    "url": "https://lapalabradeldia.com/personalizada/?p=U2FsdGVkX19iefFV5UrJq6iNQiERkJ9DDoCNnhjyXDw%3D&t=true"
  },
  {
    "gameId": 146,
    "word": "néctar",
    "url": "https://lapalabradeldia.com/personalizada/?p=U2FsdGVkX19gJ5rlKvfbXQ0xum%2B2%2FWfRVKg%2B0yDZUJc%3D&t=true"
  },
  {
    "gameId": 145,
    "word": "rímel",
    "url": "https://lapalabradeldia.com/personalizada/?p=U2FsdGVkX18aobck733KFZIgX9Hm0TCgVTYZULywjhI%3D&t=true"
  },
  {
    "gameId": 144,
    "word": "rábano",
    "url": "https://lapalabradeldia.com/personalizada/?p=U2FsdGVkX1%2BzkXHNlLNFhRpNSDg%2FoXQUg4kNc9WbwUc%3D&t=true"
  },
  {
    "gameId": 143,
    "word": "núcleo",
    "url": "https://lapalabradeldia.com/personalizada/?p=U2FsdGVkX1%2B01O3cg3i0LJv2Ext3ICHbhDCSTHh5pTU%3D&t=true"
  },
  {
    "gameId": 142,
    "word": "utópico",
    "url": "https://lapalabradeldia.com/personalizada/?p=U2FsdGVkX1%2FUazkOJyqr%2FFR4B%2Fg4GW24nfEYHSE5GyE%3D&t=true"
  },
  {
    "gameId": 141,
    "word": "icónica",
    "url": "https://lapalabradeldia.com/personalizada/?p=U2FsdGVkX19ekvpGmjQbg%2F%2BC9KBVMHW0AXkIOHDKDRo%3D&t=true"
  },
  {
    "gameId": 140,
    "word": "bóveda",
    "url": "https://lapalabradeldia.com/personalizada/?p=U2FsdGVkX198x7tfXjwndrZa8v4vS1QrW%2FipDI89ys0%3D&t=true"
  },
  {
    "gameId": 139,
    "word": "mejoría",
    "url": "https://lapalabradeldia.com/personalizada/?p=U2FsdGVkX19dw2Jmsw8V%2FeHK0PIjt4Hpf%2Bm0BWqGRgE%3D&t=true"
  },
  {
    "gameId": 138,
    "word": "paladín",
    "url": "https://lapalabradeldia.com/personalizada/?p=U2FsdGVkX1%2FOhPkrB7HmDsF2kD%2B1o%2Byc3QdPZPOwa%2BA%3D&t=true"
  },
  {
    "gameId": 137,
    "word": "júbilo",
    "url": "https://lapalabradeldia.com/personalizada/?p=U2FsdGVkX1%2FuxyHLUGBzXbmlsbd%2B1TtxTiGud7Terss%3D&t=true"
  },
  {
    "gameId": 136,
    "word": "mítico",
    "url": "https://lapalabradeldia.com/personalizada/?p=U2FsdGVkX19nyufODldXmanM%2B6npeRkFzKN%2BeJwRvzY%3D&t=true"
  },
  {
    "gameId": 135,
    "word": "lóbulo",
    "url": "https://lapalabradeldia.com/personalizada/?p=U2FsdGVkX1%2BQfuffy3vbQEGArFM2cpcI0i8BA3kRJdc%3D&t=true"
  },
  {
    "gameId": 134,
    "word": "lágrima",
    "url": "https://lapalabradeldia.com/personalizada/?p=U2FsdGVkX1%2BMENPFtWg%2FQNctMk9wF3aFfZTJLGXrfLk%3D&t=true"
  },
  {
    "gameId": 133,
    "word": "barón",
    "url": "https://lapalabradeldia.com/personalizada/?p=U2FsdGVkX19ZP2Gpi944E2o6X%2BzGYnXhlMHBAdNqiUY%3D&t=true"
  },
  {
    "gameId": 132,
    "word": "plátano",
    "url": "https://lapalabradeldia.com/personalizada/?p=U2FsdGVkX18%2FzZcKKKANrp1zHfNNgSVViUFwc8TN9Wg%3D&t=true"
  },
  {
    "gameId": 131,
    "word": "júpiter",
    "url": "https://lapalabradeldia.com/personalizada/?p=U2FsdGVkX18egSURhpZW6wHZRHW%2F8J9%2BTHcffZScI7E%3D&t=true"
  },
  {
    "gameId": 130,
    "word": "bíceps",
    "url": "https://lapalabradeldia.com/personalizada/?p=U2FsdGVkX1%2BYPsXOPD5H%2FibkccUXD5n3CRQ6MgInh%2B4%3D&t=true"
  },
  {
    "gameId": 129,
    "word": "lámina",
    "url": "https://lapalabradeldia.com/personalizada/?p=U2FsdGVkX1%2BFJ6Xbn%2BMsA7gPHDLwfAfs7bkSOlFcs2U%3D&t=true"
  },
  {
    "gameId": 128,
    "word": "período",
    "url": "https://lapalabradeldia.com/personalizada/?p=U2FsdGVkX19kXFMPxTvNFP0IGlvM%2BdKp%2By7teS86KCA%3D&t=true"
  },
  {
    "gameId": 127,
    "word": "erosión",
    "url": "https://lapalabradeldia.com/personalizada/?p=U2FsdGVkX1950eb9mt%2Flw6g9RObEQYuUvly2iWiPqkM%3D&t=true"
  },
  {
    "gameId": 126,
    "word": "teóloga",
    "url": "https://lapalabradeldia.com/personalizada/?p=U2FsdGVkX18%2BOh8nH12E0s3JvtNoC6LpHU9UJc9yTKk%3D&t=true"
  },
  {
    "gameId": 125,
    "word": "lápiz",
    "url": "https://lapalabradeldia.com/personalizada/?p=U2FsdGVkX1%2Fc2VhSq8neRR36CvXYsNjAanfJKiS1yQo%3D&t=true"
  },
  {
    "gameId": 124,
    "word": "látigo",
    "url": "https://lapalabradeldia.com/personalizada/?p=U2FsdGVkX1%2FAs0pyiSz4sBpGSBr3%2Baju9s9ZUZpphvE%3D&t=true"
  },
  {
    "gameId": 123,
    "word": "útero",
    "url": "https://lapalabradeldia.com/personalizada/?p=U2FsdGVkX1%2BdnyTR1XzyXSIi6YSLxBMQY0Se65Fs%2B%2BE%3D&t=true"
  },
  {
    "gameId": 122,
    "word": "flexión",
    "url": "https://lapalabradeldia.com/personalizada/?p=U2FsdGVkX1%2BpSjt97beY05%2FksEW7SN4Z%2BM9V%2Flj%2Bc94%3D&t=true"
  },
  {
    "gameId": 121,
    "word": "detrás",
    "url": "https://lapalabradeldia.com/personalizada/?p=U2FsdGVkX1%2BttFCTbLBz33t7RipkzYOghokSs7MwQZU%3D&t=true"
  },
  {
    "gameId": 120,
    "word": "química",
    "url": "https://lapalabradeldia.com/personalizada/?p=U2FsdGVkX1%2FBNJ4VGkC2J%2FieJpZRQAlz1udLZhT0Jvo%3D&t=true"
  },
  {
    "gameId": 119,
    "word": "música",
    "url": "https://lapalabradeldia.com/personalizada/?p=U2FsdGVkX19bd5YnsABUDSsEsVgVeJVzfE7b2hkCGAQ%3D&t=true"
  },
  {
    "gameId": 118,
    "word": "níquel",
    "url": "https://lapalabradeldia.com/personalizada/?p=U2FsdGVkX1%2FGxQZb3mmnsenb51q9%2FeMRXLql9H7dvcQ%3D&t=true"
  },
  {
    "gameId": 117,
    "word": "algún",
    "url": "https://lapalabradeldia.com/personalizada/?p=U2FsdGVkX1%2FJBS2w2L6SkktQiiMOsrsaj7cYTZAlkFI%3D&t=true"
  },
  {
    "gameId": 116,
    "word": "carbón",
    "url": "https://lapalabradeldia.com/personalizada/?p=U2FsdGVkX1%2F65DTtKHPnQD%2BBr%2BeVCA2P4KUEyc1bPog%3D&t=true"
  },
  {
    "gameId": 115,
    "word": "ácido",
    "url": "https://lapalabradeldia.com/personalizada/?p=U2FsdGVkX1%2FakFz8MHLmC7SDJtzPuL3BoG7tAkYHtiQ%3D&t=true"
  },
  {
    "gameId": 114,
    "word": "ibérico",
    "url": "https://lapalabradeldia.com/personalizada/?p=U2FsdGVkX1%2FnsOvOKrbU%2FkouhthBPnN9XdTWO%2FR0mwA%3D&t=true"
  },
  {
    "gameId": 113,
    "word": "lápida",
    "url": "https://lapalabradeldia.com/personalizada/?p=U2FsdGVkX19sh7NwMZX7qIkPrSaNj%2BX4rKZ%2BPssCBuk%3D&t=true"
  },
  {
    "gameId": 112,
    "word": "céltico",
    "url": "https://lapalabradeldia.com/personalizada/?p=U2FsdGVkX1%2BJF8p43eQY6ZLgDikAft2L3ykeoJVs8rw%3D&t=true"
  },
  {
    "gameId": 111,
    "word": "rótulo",
    "url": "https://lapalabradeldia.com/personalizada/?p=U2FsdGVkX18UYBvmIdV9wd4Z0y%2BV7MF0qvZQua8uH6k%3D&t=true"
  },
  {
    "gameId": 110,
    "word": "oxígeno",
    "url": "https://lapalabradeldia.com/personalizada/?p=U2FsdGVkX1%2BZJaOMf0lNUkRsPva19Ic5siSz%2BAsNL7Q%3D&t=true"
  },
  {
    "gameId": 109,
    "word": "músico",
    "url": "https://lapalabradeldia.com/personalizada/?p=U2FsdGVkX19xH06rcIJ%2BUc7n3yaFFH%2B%2FteFGCYcr9C0%3D&t=true"
  },
  {
    "gameId": 108,
    "word": "caníbal",
    "url": "https://lapalabradeldia.com/personalizada/?p=U2FsdGVkX19WVJxQuJ1E0d0Fd%2FQLi0JNTosJsm5UCeo%3D&t=true"
  },
  {
    "gameId": 107,
    "word": "rincón",
    "url": "https://lapalabradeldia.com/personalizada/?p=U2FsdGVkX19EI%2BKsUEChT5I8oP2yl%2FguukAZGf8Bpuk%3D&t=true"
  },
  {
    "gameId": 106,
    "word": "crédito",
    "url": "https://lapalabradeldia.com/personalizada/?p=U2FsdGVkX1%2B4YKkVG%2BWbL5KEKiHQpWQfc3Wd9ie%2FPxI%3D&t=true"
  },
  {
    "gameId": 105,
    "word": "nación",
    "url": "https://lapalabradeldia.com/personalizada/?p=U2FsdGVkX1%2BRFWoG%2BkZGV%2BYy8GOLxRr2GUFYEmXtQb0%3D&t=true"
  },
  {
    "gameId": 104,
    "word": "nítido",
    "url": "https://lapalabradeldia.com/personalizada/?p=U2FsdGVkX1%2FV3dFqnyy%2F7Iq2EuHjm1AQvZkBaB7HFKk%3D&t=true"
  },
  {
    "gameId": 103,
    "word": "caótica",
    "url": "https://lapalabradeldia.com/personalizada/?p=U2FsdGVkX19BMF6nZcpnL1PqQTU3TIx5mdKXyRZFqgI%3D&t=true"
  },
  {
    "gameId": 102,
    "word": "celíaca",
    "url": "https://lapalabradeldia.com/personalizada/?p=U2FsdGVkX1%2FOftB66qQ%2BpvpaLX9w%2F90RpaPvqA6C4Ds%3D&t=true"
  },
  {
    "gameId": 101,
    "word": "átomo",
    "url": "https://lapalabradeldia.com/personalizada/?p=U2FsdGVkX18e2NJHcTxlAsym65cce6ZVY7jo67F1ImI%3D&t=true"
  },
  {
    "gameId": 100,
    "word": "fétido",
    "url": "https://lapalabradeldia.com/personalizada/?p=U2FsdGVkX19iaffoRPIEx2Rk91a0rz1YiLojM5e7RTM%3D&t=true"
  },
  {
    "gameId": 99,
    "word": "halcón",
    "url": "https://lapalabradeldia.com/personalizada/?p=U2FsdGVkX19kVSc4ww34UBkBwLAwfzeNb4Gaf8QfVyk%3D&t=true"
  },
  {
    "gameId": 98,
    "word": "número",
    "url": "https://lapalabradeldia.com/personalizada/?p=U2FsdGVkX1%2BZSc2JL1l0maflLs%2FXVjt5l6rklCrE3YQ%3D&t=true"
  },
  {
    "gameId": 97,
    "word": "rápida",
    "url": "https://lapalabradeldia.com/personalizada/?p=U2FsdGVkX19i3vDR8k4Fa0SCUZAGy08%2BTSxAwWQYFlU%3D&t=true"
  },
  {
    "gameId": 96,
    "word": "lesión",
    "url": "https://lapalabradeldia.com/personalizada/?p=U2FsdGVkX18rNJ%2FBKmRV7mdKt1mUZak5JRTRhm0H0Ho%3D&t=true"
  },
  {
    "gameId": 95,
    "word": "cajón",
    "url": "https://lapalabradeldia.com/personalizada/?p=U2FsdGVkX19gTCcgP4ko0SbYsiY7fL%2FUV8pOt%2FlyE7s%3D&t=true"
  },
  {
    "gameId": 94,
    "word": "óvulo",
    "url": "https://lapalabradeldia.com/personalizada/?p=U2FsdGVkX18LA9QVyW5l8YaWWgSlCK%2FgclqVr4bDlwc%3D&t=true"
  },
  {
    "gameId": 93,
    "word": "fábula",
    "url": "https://lapalabradeldia.com/personalizada/?p=U2FsdGVkX1%2FsjMQDpk7n2cu7e7IqZjJIjyUiUInFGjE%3D&t=true"
  },
  {
    "gameId": 92,
    "word": "bidón",
    "url": "https://lapalabradeldia.com/personalizada/?p=U2FsdGVkX1%2B76rXQOxY3svMDkXdWd%2FeotBQfEKrQBns%3D&t=true"
  },
  {
    "gameId": 91,
    "word": "jazmín",
    "url": "https://lapalabradeldia.com/personalizada/?p=U2FsdGVkX19XaGsTDNGfnNS1ZsRdwaDzkTiTSmH9pFs%3D&t=true"
  },
  {
    "gameId": 90,
    "word": "zócalo",
    "url": "https://lapalabradeldia.com/personalizada/?p=U2FsdGVkX1%2BSLTDzIQhhncXRbNtqfNQbua7pfRklc9o%3D&t=true"
  },
  {
    "gameId": 89,
    "word": "cáscara",
    "url": "https://lapalabradeldia.com/personalizada/?p=U2FsdGVkX1%2BHovWikcu2BzSyKcbUQP%2FLyAxNyGW%2F7jI%3D&t=true"
  },
  {
    "gameId": 88,
    "word": "lácteo",
    "url": "https://lapalabradeldia.com/personalizada/?p=U2FsdGVkX1%2BlUP8ryp6WkhTcxhFBtD%2FeZ6hhteWdSmk%3D&t=true"
  },
  {
    "gameId": 87,
    "word": "búfalo",
    "url": "https://lapalabradeldia.com/personalizada/?p=U2FsdGVkX1%2FnGpDWhpLCxhI%2FHyeWUXWwCq6fgCHrz%2B8%3D&t=true"
  },
  {
    "gameId": 86,
    "word": "nómada",
    "url": "https://lapalabradeldia.com/personalizada/?p=U2FsdGVkX1908sVwvRyyJn6urEYQ8GYk%2Fndk9p8XQ2E%3D&t=true"
  },
  {
    "gameId": 85,
    "word": "déficit",
    "url": "https://lapalabradeldia.com/personalizada/?p=U2FsdGVkX180I9MAVQV%2FlP7sfatJoWFMmWb0pYMYb9Q%3D&t=true"
  },
  {
    "gameId": 84,
    "word": "pórtico",
    "url": "https://lapalabradeldia.com/personalizada/?p=U2FsdGVkX1%2FzEwYSZ%2BLXYeA%2BRELw8D4SZ1WIwBDXzX0%3D&t=true"
  },
  {
    "gameId": 83,
    "word": "futón",
    "url": "https://lapalabradeldia.com/personalizada/?p=U2FsdGVkX1%2F9fywuoY6jby%2BeB4z%2BguEHUIbUWpLrPg0%3D&t=true"
  },
  {
    "gameId": 82,
    "word": "jamón",
    "url": "https://lapalabradeldia.com/personalizada/?p=U2FsdGVkX1%2FBoWfwwMA2XpyYxfLuYBXV7yizLpuNblA%3D&t=true"
  },
  {
    "gameId": 81,
    "word": "excursión",
    "url": "https://lapalabradeldia.com/personalizada/?p=U2FsdGVkX19TSiv6cn0cvUtHrmF3amvLrOakqTCOsn8%3D&t=true"
  },
  {
    "gameId": 80,
    "word": "cómic",
    "url": "https://lapalabradeldia.com/personalizada/?p=U2FsdGVkX18HbyRZb0Iy3wYUDqFQMqnmzH99K2YKO0Y%3D&t=true"
  },
  {
    "gameId": 79,
    "word": "rústico",
    "url": "https://lapalabradeldia.com/personalizada/?p=U2FsdGVkX1%2Bt9Ky%2BbtkdSl0yJvLRnaTXXRZ6UHH%2BGjo%3D&t=true"
  },
  {
    "gameId": 78,
    "word": "botón",
    "url": "https://lapalabradeldia.com/personalizada/?p=U2FsdGVkX1%2BvUyCSWYkhplfgWMvOXtWiSGsYe9agKEg%3D&t=true"
  },
  {
    "gameId": 77,
    "word": "después",
    "url": "https://lapalabradeldia.com/personalizada/?p=U2FsdGVkX1%2B%2FQ7bOs11qp5VTqzJJiDPfK6RIBH3AqOo%3D&t=true"
  },
  {
    "gameId": 76,
    "word": "escalón",
    "url": "https://lapalabradeldia.com/personalizada/?p=U2FsdGVkX18dUb64bS7jM8%2BmVaXntEfnDtCk6fawq2E%3D&t=true"
  },
  {
    "gameId": 75,
    "word": "ratón",
    "url": "https://lapalabradeldia.com/personalizada/?p=U2FsdGVkX19n4P3cDY%2B7G14moJAejLAp4QkChIFq6fY%3D&t=true"
  },
  {
    "gameId": 74,
    "word": "lápida",
    "url": "https://lapalabradeldia.com/personalizada/?p=U2FsdGVkX18AZ5bt7cUX5DymlInoO6fjHvypybg2JlU%3D&t=true"
  },
  {
    "gameId": 73,
    "word": "glúteo",
    "url": "https://lapalabradeldia.com/personalizada/?p=U2FsdGVkX19WGZL1g1BGt5XU7IMbi2Ko4jc1R3SaS%2Bw%3D&t=true"
  },
  {
    "gameId": 72,
    "word": "errátil",
    "url": "https://lapalabradeldia.com/personalizada/?p=U2FsdGVkX18%2B44xYgv4a02cvWD2MLFESUc2SKC%2FNHnE%3D&t=true"
  },
  {
    "gameId": 71,
    "word": "difícil",
    "url": "https://lapalabradeldia.com/personalizada/?p=U2FsdGVkX19PF7u1CHCm6b2M5puZ0VHGfa1MbMJDMFQ%3D&t=true"
  },
  {
    "gameId": 70,
    "word": "jabón",
    "url": "https://lapalabradeldia.com/personalizada/?p=U2FsdGVkX1%2FlT5TB9lkcq8QTwIw%2BjP2cm1T4naNqRBI%3D&t=true"
  },
  {
    "gameId": 69,
    "word": "bólido",
    "url": "https://lapalabradeldia.com/personalizada/?p=U2FsdGVkX18evdHWucINuoTxo%2B0GUjVzu1Czr4ttO0k%3D&t=true"
  },
  {
    "gameId": 68,
    "word": "báculo",
    "url": "https://lapalabradeldia.com/personalizada/?p=U2FsdGVkX1%2B1dSUnuUOToAGArsuz2L5dtIoXGQmcVYU%3D&t=true"
  },
  {
    "gameId": 67,
    "word": "gótica",
    "url": "https://lapalabradeldia.com/personalizada/?p=U2FsdGVkX19gVRpZ24OpxKs9yknxn5Z2GwT%2FUNdUw70%3D&t=true"
  },
  {
    "gameId": 66,
    "word": "cráter",
    "url": "https://lapalabradeldia.com/personalizada/?p=U2FsdGVkX19tyJBWkdYeYG48kGBj3vxXEWnqzhxL%2BYk%3D&t=true"
  },
  {
    "gameId": 65,
    "word": "tiburón",
    "url": "https://lapalabradeldia.com/personalizada/?p=U2FsdGVkX1903W8hJ0bfPYWknla%2F1l70ST47zFOVUmE%3D&t=true"
  },
  {
    "gameId": 64,
    "word": "brújula",
    "url": "https://lapalabradeldia.com/personalizada/?p=U2FsdGVkX18Ka8XM5MerQzyQUxFuy0%2Blu937yKIBKcM%3D&t=true"
  },
  {
    "gameId": 63,
    "word": "férreo",
    "url": "https://lapalabradeldia.com/personalizada/?p=U2FsdGVkX1%2BGfdOXUbQ3hBmCxholCI84aTa%2FN2jqhZc%3D&t=true"
  },
  {
    "gameId": 62,
    "word": "inútil",
    "url": "https://lapalabradeldia.com/personalizada/?p=U2FsdGVkX1%2BHQIUwOOoD8FEFYPTqH0eJEozjSYhN70k%3D&t=true"
  },
  {
    "gameId": 61,
    "word": "fútbol",
    "url": "https://lapalabradeldia.com/personalizada/?p=U2FsdGVkX18o5sgo275VJs9RMWMmM%2Bgx%2BMkX6t7nnoM%3D&t=true"
  },
  {
    "gameId": 60,
    "word": "limón",
    "url": "https://lapalabradeldia.com/personalizada/?p=U2FsdGVkX19SA30Y7lUqrSlXhtysdX4q9z%2F3EBcGQI0%3D&t=true"
  },
  {
    "gameId": 59,
    "word": "hígado",
    "url": "https://lapalabradeldia.com/personalizada/?p=U2FsdGVkX182itLAFKEtYU538FmXI%2BxsMJKutOyMbY0%3D&t=true"
  },
  {
    "gameId": 58,
    "word": "japón",
    "url": "https://lapalabradeldia.com/personalizada/?p=U2FsdGVkX1%2FGo7QYmNqAojgmZJWZFShZchY7FmCX6zc%3D&t=true"
  },
  {
    "gameId": 57,
    "word": "círculo",
    "url": "https://lapalabradeldia.com/personalizada/?p=U2FsdGVkX18XFlEUr%2B3uA84d0Gv%2B2Rtf9JR%2FML5SOi0%3D&t=true"
  },
  {
    "gameId": 56,
    "word": "capitán",
    "url": "https://lapalabradeldia.com/personalizada/?p=U2FsdGVkX19I2YY9Gk9MXXCLkMdsMXR%2F5ua3xQUyNbc%3D&t=true"
  },
  {
    "gameId": 55,
    "word": "opción",
    "url": "https://lapalabradeldia.com/personalizada/?p=U2FsdGVkX1%2FzwFwImRz1uhg4Z47RKwe8cxe0u8q%2BZGw%3D&t=true"
  },
  {
    "gameId": 54,
    "word": "función",
    "url": "https://lapalabradeldia.com/personalizada/?p=U2FsdGVkX1%2BzXYaCsP32pdPtI%2Fcl1S2jfFxrVvZNUD8%3D&t=true"
  },
  {
    "gameId": 53,
    "word": "médico",
    "url": "https://lapalabradeldia.com/personalizada/?p=U2FsdGVkX19NVfroFIeXGOda8qIp%2Fs%2FswPHDL%2BVA0ZE%3D&t=true"
  },
  {
    "gameId": 52,
    "word": "única",
    "url": "https://lapalabradeldia.com/personalizada/?p=U2FsdGVkX18wJXdpXCAF0wbb4zakQHQNlJnofoaVIsc%3D&t=true"
  },
  {
    "gameId": 51,
    "word": "aguijón",
    "url": "https://lapalabradeldia.com/personalizada/?p=U2FsdGVkX1%2BRHnuZCW2S%2BWOdBjs8c2U4XPVbih5%2B7pc%3D&t=true"
  },
  {
    "gameId": 50,
    "word": "fémur",
    "url": "https://lapalabradeldia.com/personalizada/?p=U2FsdGVkX1%2FiIIJ5AMdaW1xLhfqZa2VQY69c%2FXYZtmU%3D&t=true"
  },
  {
    "gameId": 49,
    "word": "pícnic",
    "url": "https://lapalabradeldia.com/personalizada/?p=U2FsdGVkX1%2B25Vxk9G9bgk2Bq8hWDwQjAn4CuAoduuU%3D&t=true"
  },
  {
    "gameId": 48,
    "word": "código",
    "url": "https://lapalabradeldia.com/personalizada/?p=U2FsdGVkX1%2Bhp5%2FLWydgyDXML%2B3zu6NbL7WE3ahnteM%3D&t=true"
  },
  {
    "gameId": 47,
    "word": "pánico",
    "url": "https://lapalabradeldia.com/personalizada/?p=U2FsdGVkX187Sux5rwtUsDoPrIHerS6%2FM8JAGXAPliU%3D&t=true"
  },
  {
    "gameId": 46,
    "word": "ígnea",
    "url": "https://lapalabradeldia.com/personalizada/?p=U2FsdGVkX19UTbCXtvRaMrxVfxcGx%2BA2b%2FGWl0YiJvM%3D&t=true"
  },
  {
    "gameId": 45,
    "word": "botín",
    "url": "https://lapalabradeldia.com/personalizada/?p=U2FsdGVkX1%2BX1pq4%2BY4Ywx%2Fqia4wP6MeWhMaMvm%2BUjA%3D&t=true"
  },
  {
    "gameId": 44,
    "word": "inédita",
    "url": "https://lapalabradeldia.com/personalizada/?p=U2FsdGVkX19yGxhOym5ewprU6SBTbIJyg3y5bEpmR2g%3D&t=true"
  },
  {
    "gameId": 43,
    "word": "lúgubre",
    "url": "https://lapalabradeldia.com/personalizada/?p=U2FsdGVkX1%2BsbZw1VV1y16nxEvDIchowbEuKcfbWFKo%3D&t=true"
  },
  {
    "gameId": 42,
    "word": "coágulo",
    "url": "https://lapalabradeldia.com/personalizada/?p=U2FsdGVkX1%2B8j23uofxoq%2FE1dsAzjYy1g4Kt6jZenjg%3D&t=true"
  },
  {
    "gameId": 41,
    "word": "fusión",
    "url": "https://lapalabradeldia.com/personalizada/?p=U2FsdGVkX1%2FAkvPkxHICtwpBGmM%2FJfPvvVdXC3yKtTM%3D&t=true"
  },
  {
    "gameId": 40,
    "word": "bípedo",
    "url": "https://lapalabradeldia.com/personalizada/?p=U2FsdGVkX180zRe%2FifKVA0UYTD4uv6x03EF%2BQ2FAp08%3D&t=true"
  },
  {
    "gameId": 39,
    "word": "lógica",
    "url": "https://lapalabradeldia.com/personalizada/?p=U2FsdGVkX1%2FVjIwlisf4sOzO77btmRBXv4VMVpRdrzU%3D&t=true"
  },
  {
    "gameId": 38,
    "word": "célula",
    "url": "https://lapalabradeldia.com/personalizada/?p=U2FsdGVkX1%2FD9jsmTTcRbhxImcnnIYiHZcAKBe0rF18%3D&t=true"
  },
  {
    "gameId": 37,
    "word": "motín",
    "url": "https://lapalabradeldia.com/personalizada/?p=U2FsdGVkX1%2BQz5w5mH2UB%2FMm2r3Bvxi0%2BJEz%2BikcqTk%3D&t=true"
  },
  {
    "gameId": 36,
    "word": "cámara",
    "url": "https://lapalabradeldia.com/personalizada/?p=U2FsdGVkX19B%2FrCNNc9pqzrf3W6P6YukKr1xOTKVHqQ%3D&t=true"
  },
  {
    "gameId": 35,
    "word": "física",
    "url": "https://lapalabradeldia.com/personalizada/?p=U2FsdGVkX1%2FeyqHtLUf%2Bc3bU3AdITACQT95jjuMa1cA%3D&t=true"
  },
  {
    "gameId": 34,
    "word": "hábito",
    "url": "https://lapalabradeldia.com/personalizada/?p=U2FsdGVkX19Tczz5JzHrl1G0pjFsvxyjIAxJfboYDjs%3D&t=true"
  },
  {
    "gameId": 33,
    "word": "revés",
    "url": "https://lapalabradeldia.com/personalizada/?p=U2FsdGVkX186xBLT3Zctwmzm5yjBN0xzEq3WIDb93IA%3D&t=true"
  },
  {
    "gameId": 32,
    "word": "débil",
    "url": "https://lapalabradeldia.com/personalizada/?p=U2FsdGVkX18Rih3x0wtc4eygTrNMHZc9ZdgvN19xbeE%3D&t=true"
  },
  {
    "gameId": 31,
    "word": "acción",
    "url": "https://lapalabradeldia.com/personalizada/?p=U2FsdGVkX1%2Bvq%2Bsa4oAllY24fTBkbqDOqFaGnEkX6H0%3D&t=true"
  },
  {
    "gameId": 30,
    "word": "carié",
    "url": "https://lapalabradeldia.com/personalizada/?p=U2FsdGVkX1%2Bvq%2Bsa4oAllY24fTBkbqDOqFaGnEkX6H0%3D&t=true"
  },
  {
    "gameId": 29,
    "word": "latín",
    "url": "https://lapalabradeldia.com/personalizada/?p=U2FsdGVkX1%2BWpLCtrimHIq5QzC8xVZW%2F1xgwgPXMcYw%3D&t=true"
  },
  {
    "gameId": 28,
    "word": "líder",
    "url": "https://lapalabradeldia.com/personalizada/?p=U2FsdGVkX1%2FjJGXIv2%2BouW%2FPySoMg2MrgsdXp0%2FpjDQ%3D&t=true"
  },
  {
    "gameId": 27,
    "word": "comité",
    "url": "https://lapalabradeldia.com/personalizada/?p=U2FsdGVkX1%2F81h3exAPCfANo5ojXKv9FUH69XkLmmS4%3D&t=true"
  },
  {
    "gameId": 26,
    "word": "camisón",
    "url": "https://lapalabradeldia.com/personalizada/?p=U2FsdGVkX1%2BaxMdxtlEfsGZAQxO8tXl2MWGlGfzROyM%3D&t=true"
  },
  {
    "gameId": 25,
    "word": "ánimo",
    "url": "https://lapalabradeldia.com/personalizada/?p=U2FsdGVkX19mpYfyQC3nLTtfWraUR4dc6YskBzNXfDk%3D&t=true"
  },
  {
    "gameId": 24,
    "word": "cónsul",
    "url": "https://lapalabradeldia.com/personalizada/?p=U2FsdGVkX1%2F5n71GORQjTAophimY7BMUXW0MblN47OE%3D&t=true"
  },
  {
    "gameId": 23,
    "word": "héroe",
    "url": "https://lapalabradeldia.com/personalizada/?p=U2FsdGVkX19zc4xzxaPO5f6FgURbgNivszp%2BgAkVocM%3D&t=true"
  },
  {
    "gameId": 22,
    "word": "corazón",
    "url": "https://lapalabradeldia.com/personalizada/?p=U2FsdGVkX1%2BGnwe0%2BC6hJ%2BEf6I%2BoPPXckH13m2sphgs%3D&t=true"
  },
  {
    "gameId": 21,
    "word": "lloré",
    "url": "https://lapalabradeldia.com/personalizada/?p=U2FsdGVkX1%2Bl4YCMZEfhrO%2FFCbyQw%2FiHfUlBcfmaJ4E%3D&t=true"
  },
  {
    "gameId": 20,
    "word": "crayón",
    "url": "https://lapalabradeldia.com/personalizada/?p=U2FsdGVkX19TLh%2F98c02re4r1lK9Jc3QIzGi2ip16Wc%3D&t=true"
  },
  {
    "gameId": 19,
    "word": "fácil",
    "url": "https://lapalabradeldia.com/personalizada/?p=U2FsdGVkX1%2FpjD%2Fvyz6Rlqe5Ua21Kxkut5VUaE4tCqw%3D&t=true"
  },
  {
    "gameId": 18,
    "word": "algodón",
    "url": "https://lapalabradeldia.com/personalizada/?p=U2FsdGVkX1%2FHpY8YVCuA4eFo676VZudR7KcwP%2F1DAUg%3D&t=true"
  },
  {
    "gameId": 17,
    "word": "jamás",
    "url": "https://lapalabradeldia.com/personalizada/?p=U2FsdGVkX19jHL7JpgX%2BpYb7vJMq0Kfs1psRwjrSLl4%3D&t=true"
  },
  {
    "gameId": 16,
    "word": "policía",
    "url": "https://lapalabradeldia.com/personalizada/?p=U2FsdGVkX1%2FvqsjQqydBTyfjC1F8lA20Aw6KXcUx9jk%3D&t=true"
  },
  {
    "gameId": 15,
    "word": "úlcera",
    "url": "https://lapalabradeldia.com/personalizada/?p=U2FsdGVkX1%2FosPimVYTBSclCMXR7QGMQcO0c9PGtNUs%3D&t=true"
  },
  {
    "gameId": 14,
    "word": "encía",
    "url": "https://lapalabradeldia.com/personalizada/?p=U2FsdGVkX1%2B4t6bMQZETrXXzaWHDf00%2FMquVZdck5Os%3D&t=true"
  },
  {
    "gameId": 13,
    "word": "público",
    "url": "https://lapalabradeldia.com/personalizada/?p=U2FsdGVkX1%2BkWPweidUX9eKKx998WSFcgoVUnls%2FDqA%3D&t=true"
  },
  {
    "gameId": 12,
    "word": "camarón",
    "url": "https://lapalabradeldia.com/personalizada/?p=U2FsdGVkX1%2F4Lf3VEFrZXbzuq8RRF0ddeDlRlE%2FVlMc%3D&t=true"
  },
  {
    "gameId": 11,
    "word": "púrpura",
    "url": "https://lapalabradeldia.com/personalizada/?p=U2FsdGVkX18%2F0l%2BtcMFZGr0aO%2FGMn2xNRXXAMGhckgY%3D&t=true"
  },
  {
    "gameId": 10,
    "word": "edición",
    "url": "https://lapalabradeldia.com/personalizada/?p=U2FsdGVkX19MY48F7Cbkeso9K053jsoWG6dx4f1r5%2Fs%3D&t=true"
  },
  {
    "gameId": 9,
    "word": "césped",
    "url": "https://lapalabradeldia.com/personalizada/?p=U2FsdGVkX1%2BM5Pm1iJ5szsgPZQHhrAhZ8ID%2B2D27aHc%3D&t=true"
  },
  {
    "gameId": 8,
    "word": "cárcel",
    "url": "https://lapalabradeldia.com/personalizada/?p=U2FsdGVkX18IjxMtSjd68ui8TuPTxVJ2GE39HefWwG8%3D&t=true"
  },
  {
    "gameId": 7,
    "word": "elíxir",
    "url": "https://lapalabradeldia.com/personalizada/?p=U2FsdGVkX18coPxY%2BkXCdwhqdnHJTkmP3EKVZTwZA%2FM%3D&t=true"
  },
  {
    "gameId": 6,
    "word": "esquí",
    "url": "https://lapalabradeldia.com/personalizada/?p=U2FsdGVkX1%2Btti6Zh9Ztb8X%2BRxZzmRX0%2BTF9xm6g65Q%3D&t=true"
  },
  {
    "gameId": 5,
    "word": "calzón",
    "url": "https://lapalabradeldia.com/personalizada/?p=U2FsdGVkX1%2FOQwFP9wiucDGCbh5MtQvlJy0ZUm9YGcU%3D&t=true"
  },
  {
    "gameId": 4,
    "word": "dócil",
    "url": "https://lapalabradeldia.com/personalizada/?p=U2FsdGVkX19nvgQZcQdthNEpir%2Fafus6RuWJmz%2F%2B0tg%3D&t=true"
  },
  {
    "gameId": 3,
    "word": "prójimo",
    "url": "https://lapalabradeldia.com/personalizada/?p=U2FsdGVkX1%2B1mumTd%2FYXeOtLCPBttmp8JzIzdabBf04%3D&t=true"
  },
  {
    "gameId": 2,
    "word": "pénsum",
    "url": "https://lapalabradeldia.com/personalizada/?p=U2FsdGVkX1%2BHt4QZjV5E3fRhS5kMruXsW9izks5PMlU%3D&t=true"
  },
  {
    "gameId": 1,
    "word": "árbol",
    "url": "https://lapalabradeldia.com/personalizada/?p=U2FsdGVkX194rV8HuCmOMptRBlqnMD4SUsqBUNNMefI%3D&t=true"
  }
]