[
  {
    "gameId": 132,
    "word": "plátano",
    "url": "https://wordle.danielfrg.com/personalizada/?p=U2FsdGVkX18%2FzZcKKKANrp1zHfNNgSVViUFwc8TN9Wg%3D&t=true"
  },
  {
    "gameId": 131,
    "word": "júpiter",
    "url": "https://wordle.danielfrg.com/personalizada/?p=U2FsdGVkX18egSURhpZW6wHZRHW%2F8J9%2BTHcffZScI7E%3D&t=true"
  },
  {
    "gameId": 130,
    "word": "bíceps",
    "url": "https://wordle.danielfrg.com/personalizada/?p=U2FsdGVkX1%2BYPsXOPD5H%2FibkccUXD5n3CRQ6MgInh%2B4%3D&t=true"
  },
  {
    "gameId": 129,
    "word": "lámina",
    "url": "https://wordle.danielfrg.com/personalizada/?p=U2FsdGVkX1%2BFJ6Xbn%2BMsA7gPHDLwfAfs7bkSOlFcs2U%3D&t=true"
  },
  {
    "gameId": 128,
    "word": "período",
    "url": "https://wordle.danielfrg.com/personalizada/?p=U2FsdGVkX19kXFMPxTvNFP0IGlvM%2BdKp%2By7teS86KCA%3D&t=true"
  },
  {
    "gameId": 127,
    "word": "erosión",
    "url": "https://wordle.danielfrg.com/personalizada/?p=U2FsdGVkX1950eb9mt%2Flw6g9RObEQYuUvly2iWiPqkM%3D&t=true"
  },
  {
    "gameId": 126,
    "word": "teóloga",
    "url": "https://wordle.danielfrg.com/personalizada/?p=U2FsdGVkX18%2BOh8nH12E0s3JvtNoC6LpHU9UJc9yTKk%3D&t=true"
  },
  {
    "gameId": 125,
    "word": "lápiz",
    "url": "https://wordle.danielfrg.com/personalizada/?p=U2FsdGVkX1%2Fc2VhSq8neRR36CvXYsNjAanfJKiS1yQo%3D&t=true"
  },
  {
    "gameId": 124,
    "word": "látigo",
    "url": "https://wordle.danielfrg.com/personalizada/?p=U2FsdGVkX1%2FAs0pyiSz4sBpGSBr3%2Baju9s9ZUZpphvE%3D&t=true"
  },
  {
    "gameId": 123,
    "word": "útero",
    "url": "https://wordle.danielfrg.com/personalizada/?p=U2FsdGVkX1%2BdnyTR1XzyXSIi6YSLxBMQY0Se65Fs%2B%2BE%3D&t=true"
  },
  {
    "gameId": 122,
    "word": "flexión",
    "url": "https://wordle.danielfrg.com/personalizada/?p=U2FsdGVkX1%2BpSjt97beY05%2FksEW7SN4Z%2BM9V%2Flj%2Bc94%3D&t=true"
  },
  {
    "gameId": 121,
    "word": "detrás",
    "url": "https://wordle.danielfrg.com/personalizada/?p=U2FsdGVkX1%2BttFCTbLBz33t7RipkzYOghokSs7MwQZU%3D&t=true"
  },
  {
    "gameId": 120,
    "word": "química",
    "url": "https://wordle.danielfrg.com/personalizada/?p=U2FsdGVkX1%2FBNJ4VGkC2J%2FieJpZRQAlz1udLZhT0Jvo%3D&t=true"
  },
  {
    "gameId": 119,
    "word": "música",
    "url": "https://wordle.danielfrg.com/personalizada/?p=U2FsdGVkX19bd5YnsABUDSsEsVgVeJVzfE7b2hkCGAQ%3D&t=true"
  },
  {
    "gameId": 118,
    "word": "níquel",
    "url": "https://wordle.danielfrg.com/personalizada/?p=U2FsdGVkX1%2FGxQZb3mmnsenb51q9%2FeMRXLql9H7dvcQ%3D&t=true"
  },
  {
    "gameId": 117,
    "word": "algún",
    "url": "https://wordle.danielfrg.com/personalizada/?p=U2FsdGVkX1%2FJBS2w2L6SkktQiiMOsrsaj7cYTZAlkFI%3D&t=true"
  },
  {
    "gameId": 116,
    "word": "carbón",
    "url": "https://wordle.danielfrg.com/personalizada/?p=U2FsdGVkX1%2F65DTtKHPnQD%2BBr%2BeVCA2P4KUEyc1bPog%3D&t=true"
  },
  {
    "gameId": 115,
    "word": "ácido",
    "url": "https://wordle.danielfrg.com/personalizada/?p=U2FsdGVkX1%2FakFz8MHLmC7SDJtzPuL3BoG7tAkYHtiQ%3D&t=true"
  },
  {
    "gameId": 114,
    "word": "ibérico",
    "url": "https://wordle.danielfrg.com/personalizada/?p=U2FsdGVkX1%2FnsOvOKrbU%2FkouhthBPnN9XdTWO%2FR0mwA%3D&t=true"
  },
  {
    "gameId": 113,
    "word": "lápida",
    "url": "https://wordle.danielfrg.com/personalizada/?p=U2FsdGVkX19sh7NwMZX7qIkPrSaNj%2BX4rKZ%2BPssCBuk%3D&t=true"
  },
  {
    "gameId": 112,
    "word": "céltico",
    "url": "https://wordle.danielfrg.com/personalizada/?p=U2FsdGVkX1%2BJF8p43eQY6ZLgDikAft2L3ykeoJVs8rw%3D&t=true"
  },
  {
    "gameId": 111,
    "word": "rótulo",
    "url": "https://wordle.danielfrg.com/personalizada/?p=U2FsdGVkX18UYBvmIdV9wd4Z0y%2BV7MF0qvZQua8uH6k%3D&t=true"
  },
  {
    "gameId": 110,
    "word": "oxígeno",
    "url": "https://wordle.danielfrg.com/personalizada/?p=U2FsdGVkX1%2BZJaOMf0lNUkRsPva19Ic5siSz%2BAsNL7Q%3D&t=true"
  },
  {
    "gameId": 109,
    "word": "músico",
    "url": "https://wordle.danielfrg.com/personalizada/?p=U2FsdGVkX19xH06rcIJ%2BUc7n3yaFFH%2B%2FteFGCYcr9C0%3D&t=true"
  },
  {
    "gameId": 108,
    "word": "caníbal",
    "url": "https://wordle.danielfrg.com/personalizada/?p=U2FsdGVkX19WVJxQuJ1E0d0Fd%2FQLi0JNTosJsm5UCeo%3D&t=true"
  },
  {
    "gameId": 107,
    "word": "rincón",
    "url": "https://wordle.danielfrg.com/personalizada/?p=U2FsdGVkX19EI%2BKsUEChT5I8oP2yl%2FguukAZGf8Bpuk%3D&t=true"
  },
  {
    "gameId": 106,
    "word": "crédito",
    "url": "https://wordle.danielfrg.com/personalizada/?p=U2FsdGVkX1%2B4YKkVG%2BWbL5KEKiHQpWQfc3Wd9ie%2FPxI%3D&t=true"
  },
  {
    "gameId": 105,
    "word": "nación",
    "url": "https://wordle.danielfrg.com/personalizada/?p=U2FsdGVkX1%2BRFWoG%2BkZGV%2BYy8GOLxRr2GUFYEmXtQb0%3D&t=true"
  },
  {
    "gameId": 104,
    "word": "nítido",
    "url": "https://wordle.danielfrg.com/personalizada/?p=U2FsdGVkX1%2FV3dFqnyy%2F7Iq2EuHjm1AQvZkBaB7HFKk%3D&t=true"
  },
  {
    "gameId": 103,
    "word": "caótica",
    "url": "https://wordle.danielfrg.com/personalizada/?p=U2FsdGVkX19BMF6nZcpnL1PqQTU3TIx5mdKXyRZFqgI%3D&t=true"
  },
  {
    "gameId": 102,
    "word": "celíaca",
    "url": "https://wordle.danielfrg.com/personalizada/?p=U2FsdGVkX1%2FOftB66qQ%2BpvpaLX9w%2F90RpaPvqA6C4Ds%3D&t=true"
  },
  {
    "gameId": 101,
    "word": "átomo",
    "url": "https://wordle.danielfrg.com/personalizada/?p=U2FsdGVkX18e2NJHcTxlAsym65cce6ZVY7jo67F1ImI%3D&t=true"
  },
  {
    "gameId": 100,
    "word": "fétido",
    "url": "https://wordle.danielfrg.com/personalizada/?p=U2FsdGVkX19iaffoRPIEx2Rk91a0rz1YiLojM5e7RTM%3D&t=true"
  },
  {
    "gameId": 99,
    "word": "halcón",
    "url": "https://wordle.danielfrg.com/personalizada/?p=U2FsdGVkX19kVSc4ww34UBkBwLAwfzeNb4Gaf8QfVyk%3D&t=true"
  },
  {
    "gameId": 98,
    "word": "número",
    "url": "https://wordle.danielfrg.com/personalizada/?p=U2FsdGVkX1%2BZSc2JL1l0maflLs%2FXVjt5l6rklCrE3YQ%3D&t=true"
  },
  {
    "gameId": 97,
    "word": "rápida",
    "url": "https://wordle.danielfrg.com/personalizada/?p=U2FsdGVkX19i3vDR8k4Fa0SCUZAGy08%2BTSxAwWQYFlU%3D&t=true"
  },
  {
    "gameId": 96,
    "word": "lesión",
    "url": "https://wordle.danielfrg.com/personalizada/?p=U2FsdGVkX18rNJ%2FBKmRV7mdKt1mUZak5JRTRhm0H0Ho%3D&t=true"
  },
  {
    "gameId": 95,
    "word": "cajón",
    "url": "https://wordle.danielfrg.com/personalizada/?p=U2FsdGVkX19gTCcgP4ko0SbYsiY7fL%2FUV8pOt%2FlyE7s%3D&t=true"
  },
  {
    "gameId": 94,
    "word": "óvulo",
    "url": "https://wordle.danielfrg.com/personalizada/?p=U2FsdGVkX18LA9QVyW5l8YaWWgSlCK%2FgclqVr4bDlwc%3D&t=true"
  },
  {
    "gameId": 93,
    "word": "fábula",
    "url": "https://wordle.danielfrg.com/personalizada/?p=U2FsdGVkX1%2FsjMQDpk7n2cu7e7IqZjJIjyUiUInFGjE%3D&t=true"
  },
  {
    "gameId": 92,
    "word": "bidón",
    "url": "https://wordle.danielfrg.com/personalizada/?p=U2FsdGVkX1%2B76rXQOxY3svMDkXdWd%2FeotBQfEKrQBns%3D&t=true"
  },
  {
    "gameId": 91,
    "word": "jazmín",
    "url": "https://wordle.danielfrg.com/personalizada/?p=U2FsdGVkX19XaGsTDNGfnNS1ZsRdwaDzkTiTSmH9pFs%3D&t=true"
  },
  {
    "gameId": 90,
    "word": "zócalo",
    "url": "https://wordle.danielfrg.com/personalizada/?p=U2FsdGVkX1%2BSLTDzIQhhncXRbNtqfNQbua7pfRklc9o%3D&t=true"
  },
  {
    "gameId": 89,
    "word": "cáscara",
    "url": "https://wordle.danielfrg.com/personalizada/?p=U2FsdGVkX1%2BHovWikcu2BzSyKcbUQP%2FLyAxNyGW%2F7jI%3D&t=true"
  },
  {
    "gameId": 88,
    "word": "lácteo",
    "url": "https://wordle.danielfrg.com/personalizada/?p=U2FsdGVkX1%2BlUP8ryp6WkhTcxhFBtD%2FeZ6hhteWdSmk%3D&t=true"
  },
  {
    "gameId": 87,
    "word": "búfalo",
    "url": "https://wordle.danielfrg.com/personalizada/?p=U2FsdGVkX1%2FnGpDWhpLCxhI%2FHyeWUXWwCq6fgCHrz%2B8%3D&t=true"
  },
  {
    "gameId": 86,
    "word": "nómada",
    "url": "https://wordle.danielfrg.com/personalizada/?p=U2FsdGVkX1908sVwvRyyJn6urEYQ8GYk%2Fndk9p8XQ2E%3D&t=true"
  },
  {
    "gameId": 85,
    "word": "déficit",
    "url": "https://wordle.danielfrg.com/personalizada/?p=U2FsdGVkX180I9MAVQV%2FlP7sfatJoWFMmWb0pYMYb9Q%3D&t=true"
  },
  {
    "gameId": 84,
    "word": "pórtico",
    "url": "https://wordle.danielfrg.com/personalizada/?p=U2FsdGVkX1%2FzEwYSZ%2BLXYeA%2BRELw8D4SZ1WIwBDXzX0%3D&t=true"
  },
  {
    "gameId": 83,
    "word": "futón",
    "url": "https://wordle.danielfrg.com/personalizada/?p=U2FsdGVkX1%2F9fywuoY6jby%2BeB4z%2BguEHUIbUWpLrPg0%3D&t=true"
  },
  {
    "gameId": 82,
    "word": "jamón",
    "url": "https://wordle.danielfrg.com/personalizada/?p=U2FsdGVkX1%2FBoWfwwMA2XpyYxfLuYBXV7yizLpuNblA%3D&t=true"
  },
  {
    "gameId": 81,
    "word": "excursión",
    "url": "https://wordle.danielfrg.com/personalizada/?p=U2FsdGVkX19TSiv6cn0cvUtHrmF3amvLrOakqTCOsn8%3D&t=true"
  },
  {
    "gameId": 80,
    "word": "cómic",
    "url": "https://wordle.danielfrg.com/personalizada/?p=U2FsdGVkX18HbyRZb0Iy3wYUDqFQMqnmzH99K2YKO0Y%3D&t=true"
  },
  {
    "gameId": 79,
    "word": "rústico",
    "url": "https://wordle.danielfrg.com/personalizada/?p=U2FsdGVkX1%2Bt9Ky%2BbtkdSl0yJvLRnaTXXRZ6UHH%2BGjo%3D&t=true"
  },
  {
    "gameId": 78,
    "word": "botón",
    "url": "https://wordle.danielfrg.com/personalizada/?p=U2FsdGVkX1%2BvUyCSWYkhplfgWMvOXtWiSGsYe9agKEg%3D&t=true"
  },
  {
    "gameId": 77,
    "word": "después",
    "url": "https://wordle.danielfrg.com/personalizada/?p=U2FsdGVkX1%2B%2FQ7bOs11qp5VTqzJJiDPfK6RIBH3AqOo%3D&t=true"
  },
  {
    "gameId": 76,
    "word": "escalón",
    "url": "https://wordle.danielfrg.com/personalizada/?p=U2FsdGVkX18dUb64bS7jM8%2BmVaXntEfnDtCk6fawq2E%3D&t=true"
  },
  {
    "gameId": 75,
    "word": "ratón",
    "url": "https://wordle.danielfrg.com/personalizada/?p=U2FsdGVkX19n4P3cDY%2B7G14moJAejLAp4QkChIFq6fY%3D&t=true"
  },
  {
    "gameId": 74,
    "word": "lápida",
    "url": "https://wordle.danielfrg.com/personalizada/?p=U2FsdGVkX18AZ5bt7cUX5DymlInoO6fjHvypybg2JlU%3D&t=true"
  },
  {
    "gameId": 73,
    "word": "glúteo",
    "url": "https://wordle.danielfrg.com/personalizada/?p=U2FsdGVkX19WGZL1g1BGt5XU7IMbi2Ko4jc1R3SaS%2Bw%3D&t=true"
  },
  {
    "gameId": 72,
    "word": "errátil",
    "url": "https://wordle.danielfrg.com/personalizada/?p=U2FsdGVkX18%2B44xYgv4a02cvWD2MLFESUc2SKC%2FNHnE%3D&t=true"
  },
  {
    "gameId": 71,
    "word": "difícil",
    "url": "https://wordle.danielfrg.com/personalizada/?p=U2FsdGVkX19PF7u1CHCm6b2M5puZ0VHGfa1MbMJDMFQ%3D&t=true"
  },
  {
    "gameId": 70,
    "word": "jabón",
    "url": "https://wordle.danielfrg.com/personalizada/?p=U2FsdGVkX1%2FlT5TB9lkcq8QTwIw%2BjP2cm1T4naNqRBI%3D&t=true"
  },
  {
    "gameId": 69,
    "word": "bólido",
    "url": "https://wordle.danielfrg.com/personalizada/?p=U2FsdGVkX18evdHWucINuoTxo%2B0GUjVzu1Czr4ttO0k%3D&t=true"
  },
  {
    "gameId": 68,
    "word": "báculo",
    "url": "https://wordle.danielfrg.com/personalizada/?p=U2FsdGVkX1%2B1dSUnuUOToAGArsuz2L5dtIoXGQmcVYU%3D&t=true"
  },
  {
    "gameId": 67,
    "word": "gótica",
    "url": "https://wordle.danielfrg.com/personalizada/?p=U2FsdGVkX19gVRpZ24OpxKs9yknxn5Z2GwT%2FUNdUw70%3D&t=true"
  },
  {
    "gameId": 66,
    "word": "cráter",
    "url": "https://wordle.danielfrg.com/personalizada/?p=U2FsdGVkX19tyJBWkdYeYG48kGBj3vxXEWnqzhxL%2BYk%3D&t=true"
  },
  {
    "gameId": 65,
    "word": "tiburón",
    "url": "https://wordle.danielfrg.com/personalizada/?p=U2FsdGVkX1903W8hJ0bfPYWknla%2F1l70ST47zFOVUmE%3D&t=true"
  },
  {
    "gameId": 64,
    "word": "brújula",
    "url": "https://wordle.danielfrg.com/personalizada/?p=U2FsdGVkX18Ka8XM5MerQzyQUxFuy0%2Blu937yKIBKcM%3D&t=true"
  },
  {
    "gameId": 63,
    "word": "férreo",
    "url": "https://wordle.danielfrg.com/personalizada/?p=U2FsdGVkX1%2BGfdOXUbQ3hBmCxholCI84aTa%2FN2jqhZc%3D&t=true"
  },
  {
    "gameId": 62,
    "word": "inútil",
    "url": "https://wordle.danielfrg.com/personalizada/?p=U2FsdGVkX1%2BHQIUwOOoD8FEFYPTqH0eJEozjSYhN70k%3D&t=true"
  },
  {
    "gameId": 61,
    "word": "fútbol",
    "url": "https://wordle.danielfrg.com/personalizada/?p=U2FsdGVkX18o5sgo275VJs9RMWMmM%2Bgx%2BMkX6t7nnoM%3D&t=true"
  },
  {
    "gameId": 60,
    "word": "limón",
    "url": "https://wordle.danielfrg.com/personalizada/?p=U2FsdGVkX19SA30Y7lUqrSlXhtysdX4q9z%2F3EBcGQI0%3D&t=true"
  },
  {
    "gameId": 59,
    "word": "hígado",
    "url": "https://wordle.danielfrg.com/personalizada/?p=U2FsdGVkX182itLAFKEtYU538FmXI%2BxsMJKutOyMbY0%3D&t=true"
  },
  {
    "gameId": 58,
    "word": "japón",
    "url": "https://wordle.danielfrg.com/personalizada/?p=U2FsdGVkX1%2FGo7QYmNqAojgmZJWZFShZchY7FmCX6zc%3D&t=true"
  },
  {
    "gameId": 57,
    "word": "círculo",
    "url": "https://wordle.danielfrg.com/personalizada/?p=U2FsdGVkX18XFlEUr%2B3uA84d0Gv%2B2Rtf9JR%2FML5SOi0%3D&t=true"
  },
  {
    "gameId": 56,
    "word": "capitán",
    "url": "https://wordle.danielfrg.com/personalizada/?p=U2FsdGVkX19I2YY9Gk9MXXCLkMdsMXR%2F5ua3xQUyNbc%3D&t=true"
  },
  {
    "gameId": 55,
    "word": "opción",
    "url": "https://wordle.danielfrg.com/personalizada/?p=U2FsdGVkX1%2FzwFwImRz1uhg4Z47RKwe8cxe0u8q%2BZGw%3D&t=true"
  },
  {
    "gameId": 54,
    "word": "función",
    "url": "https://wordle.danielfrg.com/personalizada/?p=U2FsdGVkX1%2BzXYaCsP32pdPtI%2Fcl1S2jfFxrVvZNUD8%3D&t=true"
  },
  {
    "gameId": 53,
    "word": "médico",
    "url": "https://wordle.danielfrg.com/personalizada/?p=U2FsdGVkX19NVfroFIeXGOda8qIp%2Fs%2FswPHDL%2BVA0ZE%3D&t=true"
  },
  {
    "gameId": 52,
    "word": "única",
    "url": "https://wordle.danielfrg.com/personalizada/?p=U2FsdGVkX18wJXdpXCAF0wbb4zakQHQNlJnofoaVIsc%3D&t=true"
  },
  {
    "gameId": 51,
    "word": "aguijón",
    "url": "https://wordle.danielfrg.com/personalizada/?p=U2FsdGVkX1%2BRHnuZCW2S%2BWOdBjs8c2U4XPVbih5%2B7pc%3D&t=true"
  },
  {
    "gameId": 50,
    "word": "fémur",
    "url": "https://wordle.danielfrg.com/personalizada/?p=U2FsdGVkX1%2FiIIJ5AMdaW1xLhfqZa2VQY69c%2FXYZtmU%3D&t=true"
  },
  {
    "gameId": 49,
    "word": "pícnic",
    "url": "https://wordle.danielfrg.com/personalizada/?p=U2FsdGVkX1%2B25Vxk9G9bgk2Bq8hWDwQjAn4CuAoduuU%3D&t=true"
  },
  {
    "gameId": 48,
    "word": "código",
    "url": "https://wordle.danielfrg.com/personalizada/?p=U2FsdGVkX1%2Bhp5%2FLWydgyDXML%2B3zu6NbL7WE3ahnteM%3D&t=true"
  },
  {
    "gameId": 47,
    "word": "pánico",
    "url": "https://wordle.danielfrg.com/personalizada/?p=U2FsdGVkX187Sux5rwtUsDoPrIHerS6%2FM8JAGXAPliU%3D&t=true"
  },
  {
    "gameId": 46,
    "word": "ígnea",
    "url": "https://wordle.danielfrg.com/personalizada/?p=U2FsdGVkX19UTbCXtvRaMrxVfxcGx%2BA2b%2FGWl0YiJvM%3D&t=true"
  },
  {
    "gameId": 45,
    "word": "botín",
    "url": "https://wordle.danielfrg.com/personalizada/?p=U2FsdGVkX1%2BX1pq4%2BY4Ywx%2Fqia4wP6MeWhMaMvm%2BUjA%3D&t=true"
  },
  {
    "gameId": 44,
    "word": "inédita",
    "url": "https://wordle.danielfrg.com/personalizada/?p=U2FsdGVkX19yGxhOym5ewprU6SBTbIJyg3y5bEpmR2g%3D&t=true"
  },
  {
    "gameId": 43,
    "word": "lúgubre",
    "url": "https://wordle.danielfrg.com/personalizada/?p=U2FsdGVkX1%2BsbZw1VV1y16nxEvDIchowbEuKcfbWFKo%3D&t=true"
  },
  {
    "gameId": 42,
    "word": "coágulo",
    "url": "https://wordle.danielfrg.com/personalizada/?p=U2FsdGVkX1%2B8j23uofxoq%2FE1dsAzjYy1g4Kt6jZenjg%3D&t=true"
  },
  {
    "gameId": 41,
    "word": "fusión",
    "url": "https://wordle.danielfrg.com/personalizada/?p=U2FsdGVkX1%2FAkvPkxHICtwpBGmM%2FJfPvvVdXC3yKtTM%3D&t=true"
  },
  {
    "gameId": 40,
    "word": "bípedo",
    "url": "https://wordle.danielfrg.com/personalizada/?p=U2FsdGVkX180zRe%2FifKVA0UYTD4uv6x03EF%2BQ2FAp08%3D&t=true"
  },
  {
    "gameId": 39,
    "word": "lógica",
    "url": "https://wordle.danielfrg.com/personalizada/?p=U2FsdGVkX1%2FVjIwlisf4sOzO77btmRBXv4VMVpRdrzU%3D&t=true"
  },
  {
    "gameId": 38,
    "word": "célula",
    "url": "https://wordle.danielfrg.com/personalizada/?p=U2FsdGVkX1%2FD9jsmTTcRbhxImcnnIYiHZcAKBe0rF18%3D&t=true"
  },
  {
    "gameId": 37,
    "word": "motín",
    "url": "https://wordle.danielfrg.com/personalizada/?p=U2FsdGVkX1%2BQz5w5mH2UB%2FMm2r3Bvxi0%2BJEz%2BikcqTk%3D&t=true"
  },
  {
    "gameId": 36,
    "word": "cámara",
    "url": "https://wordle.danielfrg.com/personalizada/?p=U2FsdGVkX19B%2FrCNNc9pqzrf3W6P6YukKr1xOTKVHqQ%3D&t=true"
  },
  {
    "gameId": 35,
    "word": "física",
    "url": "https://wordle.danielfrg.com/personalizada/?p=U2FsdGVkX1%2FeyqHtLUf%2Bc3bU3AdITACQT95jjuMa1cA%3D&t=true"
  },
  {
    "gameId": 34,
    "word": "hábito",
    "url": "https://wordle.danielfrg.com/personalizada/?p=U2FsdGVkX19Tczz5JzHrl1G0pjFsvxyjIAxJfboYDjs%3D&t=true"
  },
  {
    "gameId": 33,
    "word": "revés",
    "url": "https://wordle.danielfrg.com/personalizada/?p=U2FsdGVkX186xBLT3Zctwmzm5yjBN0xzEq3WIDb93IA%3D&t=true"
  },
  {
    "gameId": 32,
    "word": "débil",
    "url": "https://wordle.danielfrg.com/personalizada/?p=U2FsdGVkX18Rih3x0wtc4eygTrNMHZc9ZdgvN19xbeE%3D&t=true"
  },
  {
    "gameId": 31,
    "word": "acción",
    "url": "https://wordle.danielfrg.com/personalizada/?p=U2FsdGVkX1%2Bvq%2Bsa4oAllY24fTBkbqDOqFaGnEkX6H0%3D&t=true"
  },
  {
    "gameId": 30,
    "word": "carié",
    "url": "https://wordle.danielfrg.com/personalizada/?p=U2FsdGVkX1%2Bvq%2Bsa4oAllY24fTBkbqDOqFaGnEkX6H0%3D&t=true"
  },
  {
    "gameId": 29,
    "word": "latín",
    "url": "https://wordle.danielfrg.com/personalizada/?p=U2FsdGVkX1%2BWpLCtrimHIq5QzC8xVZW%2F1xgwgPXMcYw%3D&t=true"
  },
  {
    "gameId": 28,
    "word": "líder",
    "url": "https://wordle.danielfrg.com/personalizada/?p=U2FsdGVkX1%2FjJGXIv2%2BouW%2FPySoMg2MrgsdXp0%2FpjDQ%3D&t=true"
  },
  {
    "gameId": 27,
    "word": "comité",
    "url": "https://wordle.danielfrg.com/personalizada/?p=U2FsdGVkX1%2F81h3exAPCfANo5ojXKv9FUH69XkLmmS4%3D&t=true"
  },
  {
    "gameId": 26,
    "word": "camisón",
    "url": "https://wordle.danielfrg.com/personalizada/?p=U2FsdGVkX1%2BaxMdxtlEfsGZAQxO8tXl2MWGlGfzROyM%3D&t=true"
  },
  {
    "gameId": 25,
    "word": "ánimo",
    "url": "https://wordle.danielfrg.com/personalizada/?p=U2FsdGVkX19mpYfyQC3nLTtfWraUR4dc6YskBzNXfDk%3D&t=true"
  },
  {
    "gameId": 24,
    "word": "cónsul",
    "url": "https://wordle.danielfrg.com/personalizada/?p=U2FsdGVkX1%2F5n71GORQjTAophimY7BMUXW0MblN47OE%3D&t=true"
  },
  {
    "gameId": 23,
    "word": "héroe",
    "url": "https://wordle.danielfrg.com/personalizada/?p=U2FsdGVkX19zc4xzxaPO5f6FgURbgNivszp%2BgAkVocM%3D&t=true"
  },
  {
    "gameId": 22,
    "word": "corazón",
    "url": "https://wordle.danielfrg.com/personalizada/?p=U2FsdGVkX1%2BGnwe0%2BC6hJ%2BEf6I%2BoPPXckH13m2sphgs%3D&t=true"
  },
  {
    "gameId": 21,
    "word": "lloré",
    "url": "https://wordle.danielfrg.com/personalizada/?p=U2FsdGVkX1%2Bl4YCMZEfhrO%2FFCbyQw%2FiHfUlBcfmaJ4E%3D&t=true"
  },
  {
    "gameId": 20,
    "word": "crayón",
    "url": "https://wordle.danielfrg.com/personalizada/?p=U2FsdGVkX19TLh%2F98c02re4r1lK9Jc3QIzGi2ip16Wc%3D&t=true"
  },
  {
    "gameId": 19,
    "word": "fácil",
    "url": "https://wordle.danielfrg.com/personalizada/?p=U2FsdGVkX1%2FpjD%2Fvyz6Rlqe5Ua21Kxkut5VUaE4tCqw%3D&t=true"
  },
  {
    "gameId": 18,
    "word": "algodón",
    "url": "https://wordle.danielfrg.com/personalizada/?p=U2FsdGVkX1%2FHpY8YVCuA4eFo676VZudR7KcwP%2F1DAUg%3D&t=true"
  },
  {
    "gameId": 17,
    "word": "jamás",
    "url": "https://wordle.danielfrg.com/personalizada/?p=U2FsdGVkX19jHL7JpgX%2BpYb7vJMq0Kfs1psRwjrSLl4%3D&t=true"
  },
  {
    "gameId": 16,
    "word": "policía",
    "url": "https://wordle.danielfrg.com/personalizada/?p=U2FsdGVkX1%2FvqsjQqydBTyfjC1F8lA20Aw6KXcUx9jk%3D&t=true"
  },
  {
    "gameId": 15,
    "word": "úlcera",
    "url": "https://wordle.danielfrg.com/personalizada/?p=U2FsdGVkX1%2FosPimVYTBSclCMXR7QGMQcO0c9PGtNUs%3D&t=true"
  },
  {
    "gameId": 14,
    "word": "encía",
    "url": "https://wordle.danielfrg.com/personalizada/?p=U2FsdGVkX1%2B4t6bMQZETrXXzaWHDf00%2FMquVZdck5Os%3D&t=true"
  },
  {
    "gameId": 13,
    "word": "público",
    "url": "https://wordle.danielfrg.com/personalizada/?p=U2FsdGVkX1%2BkWPweidUX9eKKx998WSFcgoVUnls%2FDqA%3D&t=true"
  },
  {
    "gameId": 12,
    "word": "camarón",
    "url": "https://wordle.danielfrg.com/personalizada/?p=U2FsdGVkX1%2F4Lf3VEFrZXbzuq8RRF0ddeDlRlE%2FVlMc%3D&t=true"
  },
  {
    "gameId": 11,
    "word": "púrpura",
    "url": "https://wordle.danielfrg.com/personalizada/?p=U2FsdGVkX18%2F0l%2BtcMFZGr0aO%2FGMn2xNRXXAMGhckgY%3D&t=true"
  },
  {
    "gameId": 10,
    "word": "edición",
    "url": "https://wordle.danielfrg.com/personalizada/?p=U2FsdGVkX19MY48F7Cbkeso9K053jsoWG6dx4f1r5%2Fs%3D&t=true"
  },
  {
    "gameId": 9,
    "word": "césped",
    "url": "https://wordle.danielfrg.com/personalizada/?p=U2FsdGVkX1%2BM5Pm1iJ5szsgPZQHhrAhZ8ID%2B2D27aHc%3D&t=true"
  },
  {
    "gameId": 8,
    "word": "cárcel",
    "url": "https://wordle.danielfrg.com/personalizada/?p=U2FsdGVkX18IjxMtSjd68ui8TuPTxVJ2GE39HefWwG8%3D&t=true"
  },
  {
    "gameId": 7,
    "word": "elíxir",
    "url": "https://wordle.danielfrg.com/personalizada/?p=U2FsdGVkX18coPxY%2BkXCdwhqdnHJTkmP3EKVZTwZA%2FM%3D&t=true"
  },
  {
    "gameId": 6,
    "word": "esquí",
    "url": "https://wordle.danielfrg.com/personalizada/?p=U2FsdGVkX1%2Btti6Zh9Ztb8X%2BRxZzmRX0%2BTF9xm6g65Q%3D&t=true"
  },
  {
    "gameId": 5,
    "word": "calzón",
    "url": "https://wordle.danielfrg.com/personalizada/?p=U2FsdGVkX1%2FOQwFP9wiucDGCbh5MtQvlJy0ZUm9YGcU%3D&t=true"
  },
  {
    "gameId": 4,
    "word": "dócil",
    "url": "https://wordle.danielfrg.com/personalizada/?p=U2FsdGVkX19nvgQZcQdthNEpir%2Fafus6RuWJmz%2F%2B0tg%3D&t=true"
  },
  {
    "gameId": 3,
    "word": "prójimo",
    "url": "https://wordle.danielfrg.com/personalizada/?p=U2FsdGVkX1%2B1mumTd%2FYXeOtLCPBttmp8JzIzdabBf04%3D&t=true"
  },
  {
    "gameId": 2,
    "word": "pénsum",
    "url": "https://wordle.danielfrg.com/personalizada/?p=U2FsdGVkX1%2BHt4QZjV5E3fRhS5kMruXsW9izks5PMlU%3D&t=true"
  },
  {
    "gameId": 1,
    "word": "árbol",
    "url": "https://wordle.danielfrg.com/personalizada/?p=U2FsdGVkX194rV8HuCmOMptRBlqnMD4SUsqBUNNMefI%3D&t=true"
  }
]